Workbook

Sheet Итоги
A1: «Старт» — итоги финансовой модели для ВТБ
A2: Горизонт: Q1 2027 – Q4 2031 (20 кварталов). Деньги — млн ₽. Значения подтягиваются с листов «Расчёт_П/Б/О»; менять нужно только лист «Допущения».
A4: Показатель | B4: Ед. | C4: Пессимистичный | D4: Базовый | E4: Оптимистичный
A5: Рынок
A6: TAM: молодёжь 14–22 в РФ | B6: тыс. чел. | C6: ='Расчёт_П'!C7 | D6: ='Расчёт_Б'!C7 | E6: ='Расчёт_О'!C7
A7: SAM: с банковской картой | B7: тыс. чел. | C7: ='Расчёт_П'!C8 | D7: ='Расчёт_Б'!C8 | E7: ='Расчёт_О'!C8
A8: SOM: клиенты ВТБ 14–22 | B8: тыс. чел. | C8: ='Расчёт_П'!C9 | D8: ='Расчёт_Б'!C9 | E8: ='Расчёт_О'!C9
A9: Проверка: клиенты ВТБ 14–25 по модели (факт ВТБ — более 4 млн) | B9: тыс. чел. | C9: ='Расчёт_П'!C10 | D9: ='Расчёт_Б'!C10 | E9: ='Расчёт_О'!C10
A10: Дроп-кейсов среди клиентов ВТБ 14–22 в год (без продукта) | B10: шт. | C10: ='Расчёт_П'!C13 | D10: ='Расчёт_Б'!C13 | E10: ='Расчёт_О'!C13
A11: Дроп-кейсов среди клиентов ВТБ 23+ в год (без продукта) | B11: шт. | C11: ='Расчёт_П'!C18 | D11: ='Расчёт_Б'!C18 | E11: ='Расчёт_О'!C18
A12: Экономика клиента
A13: Маржинальный доход на молодого клиента | B13: ₽/год | C13: ='Расчёт_П'!C14 | D13: ='Расчёт_Б'!C14 | E13: ='Расчёт_О'!C14
A14: Затраты банка на один дроп-кейс | B14: ₽ | C14: ='Расчёт_П'!C15 | D14: ='Расчёт_Б'!C15 | E14: ='Расчёт_О'!C15
A15: Инвестиции и затраты
A16: Инвестиции до полного запуска (Q1–Q3 2027) | B16: млн ₽ | C16: ='Расчёт_П'!C77 | D16: ='Расчёт_Б'!C77 | E16: ='Расчёт_О'!C77
A17: Годовые затраты в режиме эксплуатации (2031) | B17: млн ₽ | C17: ='Расчёт_П'!C81 | D17: ='Расчёт_Б'!C81 | E17: ='Расчёт_О'!C81
A18: Суммарные затраты за 5 лет | B18: млн ₽ | C18: ='Расчёт_П'!C75 | D18: ='Расчёт_Б'!C75 | E18: ='Расчёт_О'!C75
A19: Эффект за 5 лет
A20: 1. Экономия на разборе дроп-кейсов молодёжи | B20: млн ₽ | C20: ='Расчёт_П'!AC34 | D20: ='Расчёт_Б'!AC34 | E20: ='Расчёт_О'!AC34
A21: 2. Доход от сохранённых молодых клиентов | B21: млн ₽ | C21: ='Расчёт_П'!AC36 | D21: ='Расчёт_Б'!AC36 | E21: ='Расчёт_О'!AC36
A22: 3. Доход от снижения оттока | B22: млн ₽ | C22: ='Расчёт_П'!AC38 | D22: ='Расчёт_Б'!AC38 | E22: ='Расчёт_О'!AC38
A23: 4. Доход от новых клиентов | B23: млн ₽ | C23: ='Расчёт_П'!AC40 | D23: ='Расчёт_Б'!AC40 | E23: ='Расчёт_О'!AC40
A24: 5. Экономия контакт-центра | B24: млн ₽ | C24: ='Расчёт_П'!AC42 | D24: ='Расчёт_Б'!AC42 | E24: ='Расчёт_О'!AC42
A25: 8. Мост «Детский банк» → «Старт» | B25: млн ₽ | C25: ='Расчёт_П'!AC45 | D25: ='Расчёт_Б'!AC45 | E25: ='Расчёт_О'!AC45
A26: 9. Клиенты из «Пушкинской карты» | B26: млн ₽ | C26: ='Расчёт_П'!AC47 | D26: ='Расчёт_Б'!AC47 | E26: ='Расчёт_О'!AC47
A27: 6. Этап 2: экономия на дроп-кейсах 23+ | B27: млн ₽ | C27: ='Расчёт_П'!AC50 | D27: ='Расчёт_Б'!AC50 | E27: ='Расчёт_О'!AC50
A28: 7. Этап 2: доход от сохранённых взрослых клиентов | B28: млн ₽ | C28: ='Расчёт_П'!AC52 | D28: ='Расчёт_Б'!AC52 | E28: ='Расчёт_О'!AC52
A29: Суммарный эффект за 5 лет | B29: млн ₽ | C29: ='Расчёт_П'!C74 | D29: ='Расчёт_Б'!C74 | E29: ='Расчёт_О'!C74
A30: Годовой эффект (2031) | B30: млн ₽ | C30: ='Расчёт_П'!C82 | D30: ='Расчёт_Б'!C82 | E30: ='Расчёт_О'!C82
A31: Операционный поток 2029 (эффект минус затраты) | B31: млн ₽ | C31: ='Расчёт_П'!C83 | D31: ='Расчёт_Б'!C83 | E31: ='Расчёт_О'!C83
A32: Окупаемость
A33: NPV за 5 лет (2027–2031) | B33: млн ₽ | C33: ='Расчёт_П'!C71 | D33: ='Расчёт_Б'!C71 | E33: ='Расчёт_О'!C71
A34: NPV за 5 лет только ядра продукта | B34: млн ₽ | C34: ='Расчёт_П'!C72 | D34: ='Расчёт_Б'!C72 | E34: ='Расчёт_О'!C72
A35: NPV за первые 3 года (справочно) | B35: млн ₽ | C35: ='Расчёт_П'!C73 | D35: ='Расчёт_Б'!C73 | E35: ='Расчёт_О'!C73
A36: ROI за 5 лет | B36: доля | C36: ='Расчёт_П'!C76 | D36: ='Расчёт_Б'!C76 | E36: ='Расчёт_О'!C76
A37: Срок окупаемости от старта проекта | B37: мес. | C37: ='Расчёт_П'!C79 | D37: ='Расчёт_Б'!C79 | E37: ='Расчёт_О'!C79
A38: Срок окупаемости от полного запуска | B38: мес. | C38: ='Расчёт_П'!C80 | D38: ='Расчёт_Б'!C80 | E38: ='Расчёт_О'!C80
A39: Клиенты и общество (вне NPV)
A40: MAU раздела на конец 2031 | B40: тыс. чел. | C40: ='Расчёт_П'!C87 | D40: ='Расчёт_Б'!C87 | E40: ='Расчёт_О'!C87
A41: Предотвращено дроп-кейсов молодёжи за 5 лет | B41: шт. | C41: ='Расчёт_П'!C84 | D41: ='Расчёт_Б'!C84 | E41: ='Расчёт_О'!C84
A42: Предотвращено дроп-кейсов 23+ за 5 лет | B42: шт. | C42: ='Расчёт_П'!C85 | D42: ='Расчёт_Б'!C85 | E42: ='Расчёт_О'!C85
A43: Молодых клиентов сохранено, удержано и привлечено (конец 2031) | B43: чел. | C43: ='Расчёт_П'!C88 | D43: ='Расчёт_Б'!C88 | E43: ='Расчёт_О'!C88
A44: Стратегическая ценность этих клиентов после 23 лет | B44: млн ₽ | C44: ='Расчёт_П'!C89 | D44: ='Расчёт_Б'!C89 | E44: ='Расчёт_О'!C89
A45: Чужих денег не прошло через карты ВТБ | B45: млн ₽ | C45: ='Расчёт_П'!C86 | D45: ='Расчёт_Б'!C86 | E45: ='Расчёт_О'!C86
A46: Затраты на одного MAU в 2031 | B46: ₽/год | C46: ='Расчёт_П'!C90 | D46: ='Расчёт_Б'!C90 | E46: ='Расчёт_О'!C90
A48: Накопленный денежный поток, млн ₽ (для графика)
A49: Квартал | B49: Пессимистичный | C49: Базовый | D49: Оптимистичный
A50: Q1 2027 | B50: ='Расчёт_П'!C65 | C50: ='Расчёт_Б'!C65 | D50: ='Расчёт_О'!C65
A51: Q2 2027 | B51: ='Расчёт_П'!D65 | C51: ='Расчёт_Б'!D65 | D51: ='Расчёт_О'!D65
A52: Q3 2027 | B52: ='Расчёт_П'!E65 | C52: ='Расчёт_Б'!E65 | D52: ='Расчёт_О'!E65
A53: Q4 2027 | B53: ='Расчёт_П'!F65 | C53: ='Расчёт_Б'!F65 | D53: ='Расчёт_О'!F65
A54: Q1 2028 | B54: ='Расчёт_П'!G65 | C54: ='Расчёт_Б'!G65 | D54: ='Расчёт_О'!G65
A55: Q2 2028 | B55: ='Расчёт_П'!H65 | C55: ='Расчёт_Б'!H65 | D55: ='Расчёт_О'!H65
A56: Q3 2028 | B56: ='Расчёт_П'!I65 | C56: ='Расчёт_Б'!I65 | D56: ='Расчёт_О'!I65
A57: Q4 2028 | B57: ='Расчёт_П'!J65 | C57: ='Расчёт_Б'!J65 | D57: ='Расчёт_О'!J65
A58: Q1 2029 | B58: ='Расчёт_П'!K65 | C58: ='Расчёт_Б'!K65 | D58: ='Расчёт_О'!K65
A59: Q2 2029 | B59: ='Расчёт_П'!L65 | C59: ='Расчёт_Б'!L65 | D59: ='Расчёт_О'!L65
A60: Q3 2029 | B60: ='Расчёт_П'!M65 | C60: ='Расчёт_Б'!M65 | D60: ='Расчёт_О'!M65
A61: Q4 2029 | B61: ='Расчёт_П'!N65 | C61: ='Расчёт_Б'!N65 | D61: ='Расчёт_О'!N65
A62: Q1 2030 | B62: ='Расчёт_П'!O65 | C62: ='Расчёт_Б'!O65 | D62: ='Расчёт_О'!O65
A63: Q2 2030 | B63: ='Расчёт_П'!P65 | C63: ='Расчёт_Б'!P65 | D63: ='Расчёт_О'!P65
A64: Q3 2030 | B64: ='Расчёт_П'!Q65 | C64: ='Расчёт_Б'!Q65 | D64: ='Расчёт_О'!Q65
A65: Q4 2030 | B65: ='Расчёт_П'!R65 | C65: ='Расчёт_Б'!R65 | D65: ='Расчёт_О'!R65
A66: Q1 2031 | B66: ='Расчёт_П'!S65 | C66: ='Расчёт_Б'!S65 | D66: ='Расчёт_О'!S65
A67: Q2 2031 | B67: ='Расчёт_П'!T65 | C67: ='Расчёт_Б'!T65 | D67: ='Расчёт_О'!T65
A68: Q3 2031 | B68: ='Расчёт_П'!U65 | C68: ='Расчёт_Б'!U65 | D68: ='Расчёт_О'!U65
A69: Q4 2031 | B69: ='Расчёт_П'!V65 | C69: ='Расчёт_Б'!V65 | D69: ='Расчёт_О'!V65
A72: Как читать модель
A73: Синий шрифт — вводные (лист «Допущения»), чёрный — формулы, зелёный — ссылки на другие листы.
A74: Жёлтая заливка — ключевые допущения: доля ВТБ у молодёжи, эффект продукта, охват, привлечение. Их подтверждаем на пилоте.
A75: Эффект — только в деньгах ВТБ. Возврат денег жертвам и снижение регуляторного риска показаны отдельно и в NPV не входят.
A76: Доход от клиентов считается как поток маржинального дохода по накопленной базе клиентов с учётом оттока, а не LTV разом.

Sheet Допущения
A1: Допущения финансовой модели «Старт» (антидроп + финграмотность для клиентов 14–22)
A2: Синий шрифт — вводные, их можно менять. Жёлтая заливка — ключевые допущения, которые нужно подтвердить данными ВТБ на пилоте. Чёрный — формулы. Зелёный — ссылки на другие листы.
A4: Допущение | B4: Единица | C4: Пессимистичный | D4: Базовый | E4: Оптимистичный | F4: Источник / обоснование
A6: 1. Рынок и аудитория
A7: Родилось в 2004–2008 гг. (в 2026 им 18–22 года) | B7: тыс. чел. | C7: 7763.5 | D7: 7763.5 | E7: 7763.5 | F7: Росстат, число родившихся по годам: 2004 — 1502,5; 2005 — 1457,4; 2006 — 1479,6; 2007 — 1610,1; 2008 — 1713,9 тыс. Оценка когорты; сверить с численностью населения по возрастам на 01.01.2026 (Росстат).
A8: Родилось в 2009–2012 гг. (в 2026 им 14–17 лет) | B8: тыс. чел. | C8: 7249.3 | D8: 7249.3 | E8: 7249.3 | F8: Росстат: 2009 — 1761,7; 2010 — 1788,9; 2011 — 1796,6; 2012 — 1902,1 тыс.
A9: Коэффициент дожития и миграции когорты | B9: доля | C9: 0.97 | D9: 0.97 | E9: 0.97 | F9: Допущение: смертность в возрасте 0–22 и сальдо миграции. Уточнить по Росстату.
A10: Доля 14–17 лет со своей банковской картой | B10: доля | C10: 0.7 | D10: 0.75 | E10: 0.8 | F10: Допущение. Карта с 14 лет — массовый продукт у всех крупных банков; с лета 2025 нужно согласие родителей.
A11: Доля 18–22 лет с банковской картой | B11: доля | C11: 0.95 | D11: 0.95 | E11: 0.95 | F11: Допущение: стипендии и зарплаты зачисляются на карту, проникновение близко к взрослому.
A12: Доля ВТБ среди 14–17 лет с картой | B12: доля | C12: 0.13 | D12: 0.17 | E12: 0.2 | F12: Калибровка по факту: у ВТБ более 4 млн клиентов 14–25 лет (ВТБ, июнь 2026). Подростков у ВТБ меньше, чем 18–25, поэтому доля 14–17 ≈ 0,6 от доли 18–25. Проверка — строка «клиенты ВТБ 14–25 по модели» на листах расчёта. Пессимистичный сценарий ниже: часть из 4 млн — неактивные клиенты. https://abnews.ru/news/2026/6/1/vtb-zapustit-nakopitelnyj-schet-dlya-molodezhi
A13: Доля ВТБ среди 18–25 лет с картой | B13: доля | C13: 0.22 | D13: 0.28 | E13: 0.32 | F13: Калибровка по факту 4 млн клиентов 14–25 (см. выше). Для сравнения: 30,3 млн активных розничных клиентов ВТБ на конец 2025 г. ≈ четверть банковского населения. https://finance.rambler.ru/business/55672832/
A14: Дропов выявляет ЦБ в месяц (2026) | B14: чел./мес | C14: 40000 | D14: 40000 | E14: 40000 | F14: Б. Шабля (ЦБ), 23.09.2026: ~100 тыс./мес в 2025 → не более 40 тыс./мес в 2026. https://www.interfax.ru/business/1117991 (docs/research/evidence.md № 5)
A15: Доля людей 14–22 лет среди дропов | B15: доля | C15: 0.4 | D15: 0.45 | E15: 0.5 | F15: ЦБ: более 50% базы дропов — моложе 25 лет (А. Афонин, сент. 2026); 14–22 — часть этой группы. Несовершеннолетних среди дроп-счетов 16% (Шабля, I пол. 2026).
A16: Родилось в 2001–2003 гг. (в 2026 им 23–25 лет) — для сверки с фактом ВТБ | B16: тыс. чел. | C16: 4185.8 | D16: 4185.8 | E16: 4185.8 | F16: Росстат: 2001 — 1311,6; 2002 — 1397,0; 2003 — 1477,3 тыс.
A17: Факт: клиентов ВТБ 14–25 лет | B17: тыс. чел. | C17: 4000 | D17: 4000 | E17: 4000 | F17: ВТБ, июнь 2026: «клиентская база банка в возрасте 14–25 лет превышает 4 млн человек». https://abnews.ru/news/2026/6/1/vtb-zapustit-nakopitelnyj-schet-dlya-molodezhi
A19: 2. Экономика молодого клиента
A20: Средние траты по карте молодого клиента | B20: ₽/мес | C20: 10000 | D20: 12000 | E20: 14000 | F20: Допущение (смесь 14–17 и 18–22). Уточнить по данным ВТБ.
A21: Чистый комиссионный доход с оборота (интерчейндж минус расходы и кешбэк) | B21: доля | C21: 0.008 | D21: 0.008 | E21: 0.008 | F21: Допущение: интерчейндж по картам «Мир» ~1–1,5% минус кешбэк и процессинг.
A22: Средний остаток на счетах молодого клиента | B22: ₽ | C22: 6000 | D22: 8000 | E22: 10000 | F22: Допущение. Клиенты 14–25 хранят > 60 млрд ₽ на накопительных счетах ВТБ (июнь 2026).
A23: Процентная маржа на пассивах | B23: доля/год | C23: 0.04 | D23: 0.04 | E23: 0.04 | F23: Допущение: размещение по ставке, близкой к ключевой (14%, ЦБ 11.09.2026), минус ставка по счёту.
A24: Расходы на обслуживание молодого клиента | B24: ₽/год | C24: 400 | D24: 400 | E24: 400 | F24: Допущение: выпуск карты, поддержка, ИТ.
A25: Годовой отток молодых клиентов | B25: доля/год | C25: 0.15 | D25: 0.15 | E25: 0.15 | F25: Допущение. Уточнить по когортам ВТБ.
A27: 3. Затраты банка на один дроп-кейс
A28: Часы антифрод-аналитика на расследование и блокировку | B28: ч | C28: 2 | D28: 2 | E28: 2 | F28: Допущение: разбор операций, блокировка, обмен с ФинЦЕРТ.
A29: Полная стоимость часа аналитика | B29: ₽/ч | C29: 1800 | D29: 1800 | E29: 1800 | F29: Допущение: ~250 тыс. ₽/мес брутто × 1,5 / 165 ч.
A30: Звонков в контакт-центр по одному кейсу | B30: шт. | C30: 3 | D30: 3 | E30: 3 | F30: Допущение: блокировка, разбор, разблокировка.
A31: Стоимость одного звонка в контакт-центр | B31: ₽ | C31: 250 | D31: 250 | E31: 250 | F31: Допущение: ~5 мин × ~50 ₽/мин полной стоимости оператора. Публичных данных банков нет.
A32: Доля кейсов с обжалованием (база ЦБ, жалобы) | B32: доля | C32: 0.5 | D32: 0.5 | E32: 0.5 | F32: Допущение. ЦБ: > 50% заявлений об исключении из базы — от людей моложе 25 лет (evidence.md № 3).
A33: Стоимость обработки обжалования | B33: ₽ | C33: 1500 | D33: 1500 | E33: 1500 | F33: Допущение: ~1 ч специалиста.
A34: Прочие операционные расходы на кейс (отчётность, документы) | B34: ₽ | C34: 500 | D34: 500 | E34: 500 | F34: Допущение.
A35: Доля дроп-кейсов, после которых клиент потерян | B35: доля | C35: 0.7 | D35: 0.7 | E35: 0.7 | F35: Допущение: ограничение ДБО, закрытие счетов, уход клиента.
A36: Чужих денег проходит через один дроп-счёт (для социального эффекта) | B36: ₽ | C36: 150000 | D36: 150000 | E36: 150000 | F36: Оценка: средний чек хищения 18,6 тыс. ₽ (ЦБ, обзор за 2025) × ~8 операций до блокировки. В NPV не входит.
A38: 4. Эффект продукта (гипотезы, проверяем на пилоте)
A39: Доля дроп-кейсов молодёжи, которые остановит перехват перевода + «Безопасный выход» | B39: доля | C39: 0.08 | D39: 0.15 | E39: 0.25 | F39: Гипотеза для A/B-пилота. Перехват работает в переводах у ВСЕХ молодых клиентов, не только у пользователей раздела. На синтетике CatBoost ловит 99% транзитов при 0,9% ложных перехватов (ml/reports/metrics.md), но в жизни часть людей продолжит, а часть схем идёт мимо переводов (передача карты, наличные) — поэтому берём 8–25%.
A40: Дополнительное снижение у активных пользователей раздела (уроки, квест, Щит) | B40: доля | C40: 0.03 | D40: 0.1 | E40: 0.15 | F40: Гипотеза: тот, кто прошёл урок про дропов или проверил сообщение в Щите, реже соглашается на «подработку».
A41: Снижение оттока у пользователей раздела | B41: п.п./год | C41: 0.005 | D41: 0.015 | E41: 0.025 | F41: Гипотеза: регулярное использование раздела (уроки, XP, защита) повышает вовлечённость.
A42: Обращений в КЦ о блокировках и мошенничестве на молодого клиента | B42: шт./год | C42: 0.05 | D42: 0.1 | E42: 0.15 | F42: Допущение. ЦБ: жалоб на отказы и ограничения стало вшестеро больше — 23,8 тыс. за янв.–июль 2026 (evidence.md № 18).
A43: Доля обращений, закрытых самообслуживанием («Безопасный выход», объяснения) | B43: доля | C43: 0.25 | D43: 0.4 | E43: 0.5 | F43: Гипотеза: объяснение причины на экране + пошаговый план без звонка.
A44: Привлечение новых молодых клиентов ВТБ в год (без продукта) | B44: чел./год | C44: 450000 | D44: 450000 | E44: 450000 | F44: Допущение: чтобы база ~2,9 млн не сокращалась при оттоке 15%, банку нужно привлекать ~450 тыс. молодых клиентов в год. ЗАПРОСИТЬ У ВТБ.
A45: Прирост привлечения благодаря продукту | B45: доля | C45: 0.01 | D45: 0.03 | E45: 0.05 | F45: Гипотеза: «банк, который защищает подростка» — аргумент для родителей; партнёрства со школами и вузами.
A47: 4б. Масштабирование перехвата на клиентов 23+ (этап 2)
A48: Включить этап 2 (1 — да, 0 — нет) | B48: 0/1 | C48: 1 | D48: 1 | E48: 1 | F48: Движок перехвата и «Безопасный выход» не зависят от возраста: после пилота на молодёжи их можно включить для всех.
A49: Квартал запуска этапа 2 (номер периода) | B49: № | C49: 6 | D49: 6 | E49: 6 | F49: Q2 2028 — после полугода работы на молодёжи.
A50: Доля людей 23+ среди дропов | B50: доля | C50: 0.5 | D50: 0.5 | E50: 0.5 | F50: ЦБ: более 50% базы дропов моложе 25 лет → 23+ — около половины.
A51: Доля дроп-кейсов 23+, приходящихся на ВТБ | B51: доля | C51: 0.1 | D51: 0.13 | E51: 0.16 | F51: Допущение: ВТБ — 30,3 млн активных клиентов (≈ четверть банковского населения), но дропы уходят в небольшие банки (ЦБ, РГ 17.04.2025) — берём ниже доли рынка. ЗАПРОСИТЬ У ВТБ.
A52: Доля дроп-кейсов 23+, которые остановит перехват | B52: доля | C52: 0.04 | D52: 0.08 | E52: 0.12 | F52: Гипотеза: взрослые дропы чаще действуют осознанно, эффект ниже, чем у молодёжи.
A53: Маржинальный доход взрослого розничного клиента | B53: ₽/год | C53: 2000 | D53: 3000 | E53: 4000 | F53: Допущение. Розница ВТБ вышла в прибыль в 2026 г. после убытка в 2025 г. Уточнить по сегментной отчётности МСФО.
A54: Годовой отток взрослых клиентов | B54: доля/год | C54: 0.1 | D54: 0.1 | E54: 0.1 | F54: Допущение.
A56: 4в. Стратегическая ценность молодого клиента (вне NPV)
A57: Доля молодых клиентов, которые остаются в банке после 23 лет | B57: доля | C57: 0.3 | D57: 0.4 | E57: 0.5 | F57: Допущение. Смысл молодёжных продуктов банков — «клиент с 14 лет»: зарплатный проект, кредиты, ипотека.
A58: Лет в среднем до 23 лет | B58: лет | C58: 4 | D58: 4 | E58: 4 | F58: Средний клиент 14–22 → ~4 года до 23.
A59: Горизонт взрослой жизни клиента в банке для оценки | B59: лет | C59: 7 | D59: 7 | E59: 7 | F59: Консервативно.
A61: 4г. Мост из «Детского банка» и «Пушкинская карта» (новые каналы)
A62: Включить мост «Детский банк» → «Старт» (1 — да, 0 — нет) | B62: 0/1 | C62: 1 | D62: 1 | E62: 1 | F62: Сценарный переключатель.
A63: Детей, которым исполняется 14 лет, в год | B63: чел./год | C63: 1900000 | D63: 1900000 | E63: 1900000 | F63: Росстат: родилось 1 902 тыс. в 2012 г. и 1 896 тыс. в 2013 г.
A64: Доля из них с картой «Детского банка» ВТБ | B64: доля | C64: 0.04 | D64: 0.06 | E64: 0.08 | F64: Допущение: «Детский банк» запущен в сент. 2026; к 2028 г. — 4–8% когорты. ЗАПРОСИТЬ У ВТБ.
A65: Сколько из них дополнительно останутся в ВТБ благодаря мосту | B65: доля | C65: 0.05 | D65: 0.1 | E65: 0.15 | F65: Гипотеза: у конкурентов (Сбер, Т-Банк, Альфа) в 14 лет нужна новая заявка на новый продукт, и в этот момент подросток уходит; мост переносит цели, копилку и XP в «Старт» в одно касание (docs/research/competitors.md, раздел 4).
A66: Включить канал «Пушкинской карты» (1 — да, 0 — нет) | B66: 0/1 | C66: 1 | D66: 1 | E66: 1 | F66: Сценарный переключатель.
A67: Новых держателей «Пушкинской карты» ВТБ в год | B67: чел./год | C67: 1200000 | D67: 1500000 | E67: 1700000 | F67: ВТБ — оператор программы с 01.01.2026; почти 7 млн карт за январь–май 2026 (перевыпуск). В устойчивом режиме — новые 14-летние (~1,9 млн/год) × участие в программе. https://lenta.ru/news/2026/06/01/vtb-rasskazal-o-programme-pushkinskaya-karta/
A68: Доля держателей, которые ещё не пользуются обычными продуктами ВТБ | B68: доля | C68: 0.7 | D68: 0.7 | E68: 0.7 | F68: Допущение: «Пушкинская карта» оформляется и через Госуслуги Культура, без счёта в ВТБ.
A69: Конверсия держателей в клиентов ВТБ через витрину «Старта» | B69: доля | C69: 0.01 | D69: 0.02 | E69: 0.04 | F69: Гипотеза: «Старт» показываем каждому держателю в ВТБ Онлайн; повод открыть свою карту — защита, копилка, партнёрские офферы.
A71: 5. Внедрение
A72: Множитель кривой охвата (к базовой кривой ниже) | B72: x | C72: 0.6 | D72: 1 | E72: 1.25 | F72: Сценарный рычаг охвата.
A73: Потолок охвата | B73: доля | C73: 0.6 | D73: 0.6 | E73: 0.6 | F73: Не больше 60% молодых клиентов пользуются разделом ежемесячно.
A74: Кварталов разработки и пилота (полная команда) | B74: кв. | C74: 3 | D74: 3 | E74: 3 | F74: Q1–Q2 2027 — разработка и интеграция в ВТБ Онлайн, Q3 2027 — пилот (A/B в 1–2 регионах).
A75: Квартал полного запуска (номер периода) | B75: № | C75: 4 | D75: 4 | E75: 4 | F75: Q4 2027.
A76: Страховые взносы на ФОТ | B76: доля | C76: 0.3 | D76: 0.3 | E76: 0.3 | F76: НК РФ: единый тариф 30% (упрощённо).
A77: Накладные расходы на сотрудника (рабочее место, лицензии) | B77: доля | C77: 0.15 | D77: 0.15 | E77: 0.15 | F77: Допущение.
A78: Вознаграждения пользователям за счёт банка (геймификация) | B78: ₽/MAU/год | C78: 30 | D78: 20 | E78: 15 | F78: Допущение: промо-кешбэк за уроки и квест. Основную часть призов (кино, игры, мерч) дают партнёры за размещение.
A79: Резерв на непредвиденные расходы | B79: доля | C79: 0.1 | D79: 0.1 | E79: 0.1 | F79: Стандартный резерв проекта.
A80: Коэффициент перерасхода бюджета | B80: x | C80: 1.2 | D80: 1 | E80: 0.95 | F80: Сценарный рычаг затрат.
A81: Ставка дисконтирования | B81: доля/год | C81: 0.2 | D81: 0.18 | E81: 0.16 | F81: Ключевая ставка 14% (ЦБ, 11.09.2026) + премия за риск проекта 2–6 п.п.
A83: 6. Команда (месячная зарплата брутто, тыс. ₽)
A84: Роль | B84: Зарплата, тыс. ₽/мес | C84: FTE: разработка и пилот | D84: FTE: эксплуатация | F84: Обоснование
A85: Продакт-менеджер | B85: 400 | C85: 1 | D85: 0.5 | F85: Вилки middle в Москве 2026: 185–360 тыс. ₽/мес (Хабр Карьера, вакансии), финтех — верх вилки. https://career.habr.com/vacancies/spec/development/backend
A86: Backend-разработчик | B86: 330 | C86: 2 | D86: 1
A87: Мобильный разработчик (iOS/Android, ВТБ Онлайн) | B87: 340 | C87: 2 | D87: 1
A88: ML-инженер | B88: 370 | C88: 1 | D88: 1
A89: Аналитик данных | B89: 260 | C89: 1 | D89: 0.5
A90: QA-инженер | B90: 230 | C90: 1 | D90: 0.5
A91: Дизайнер | B91: 260 | C91: 1 | D91: 0
A92: Специалист ИБ / комплаенс (152-ФЗ, 115-ФЗ) | B92: 360 | C92: 0.5 | D92: 0.25
A93: Методист и юрист по контенту | B93: 200 | C93: 0.5 | D93: 0.25
A94: Итого FTE | C94: =SUM(C85:C93) | D94: =SUM(D85:D93)
A97: 7. Кривая охвата и график затрат по кварталам (колонки C–V = Q1 2027 … Q4 2031)
A98: Период | C98: Q1 2027 | D98: Q2 2027 | E98: Q3 2027 | F98: Q4 2027 | G98: Q1 2028 | H98: Q2 2028 | I98: Q3 2028 | J98: Q4 2028 | K98: Q1 2029 | L98: Q2 2029 | M98: Q3 2029 | N98: Q4 2029 | O98: Q1 2030 | P98: Q2 2030 | Q98: Q3 2030 | R98: Q4 2030 | S98: Q1 2031 | T98: Q2 2031 | U98: Q3 2031 | V98: Q4 2031
A99: Охват: доля молодых клиентов ВТБ — MAU раздела (базовая кривая) | B99: доля | C99: 0 | D99: 0 | E99: 0.02 | F99: 0.08 | G99: 0.14 | H99: 0.2 | I99: 0.25 | J99: 0.28 | K99: 0.31 | L99: 0.33 | M99: 0.35 | N99: 0.36 | O99: 0.37 | P99: 0.38 | Q99: 0.39 | R99: 0.4 | S99: 0.4 | T99: 0.4 | U99: 0.4 | V99: 0.4
A100: Покрытие перехватом: доля молодых клиентов, у которых включён перехват | B100: доля | C100: 0 | D100: 0 | E100: 0.05 | F100: 1 | G100: 1 | H100: 1 | I100: 1 | J100: 1 | K100: 1 | L100: 1 | M100: 1 | N100: 1 | O100: 1 | P100: 1 | Q100: 1 | R100: 1 | S100: 1 | T100: 1 | U100: 1 | V100: 1
A101: Сервер для on-prem LLM (GPU): покупка и обновление в 2030 | B101: млн ₽ | C101: 6 | D101: 0 | E101: 0 | F101: 0 | G101: 0 | H101: 0 | I101: 0 | J101: 0 | K101: 0 | L101: 0 | M101: 0 | N101: 0 | O101: 0 | P101: 2 | Q101: 0 | R101: 0 | S101: 0 | T101: 0 | U101: 0 | V101: 0
A102: Частное облако ВТБ: сервисы, БД, мониторинг | B102: млн ₽ | C102: 0 | D102: 0.45 | E102: 0.45 | F102: 0.45 | G102: 0.45 | H102: 0.45 | I102: 0.45 | J102: 0.45 | K102: 0.45 | L102: 0.45 | M102: 0.45 | N102: 0.45 | O102: 0.45 | P102: 0.45 | Q102: 0.45 | R102: 0.45 | S102: 0.45 | T102: 0.45 | U102: 0.45 | V102: 0.45
A103: Аудит ИБ, пентест, оценка соответствия 152-ФЗ | B103: млн ₽ | C103: 0 | D103: 0 | E103: 3 | F103: 0 | G103: 0 | H103: 0 | I103: 0 | J103: 1 | K103: 0 | L103: 0 | M103: 0 | N103: 1 | O103: 0 | P103: 0 | Q103: 0 | R103: 1 | S103: 0 | T103: 0 | U103: 0 | V103: 1
A104: Контент и юридическая экспертиза (уроки, SOS, квесты) | B104: млн ₽ | C104: 0 | D104: 1.5 | E104: 0 | F104: 0.3 | G104: 0.3 | H104: 0.3 | I104: 0.3 | J104: 0.3 | K104: 0.3 | L104: 0.3 | M104: 0.3 | N104: 0.3 | O104: 0.3 | P104: 0.3 | Q104: 0.3 | R104: 0.3 | S104: 0.3 | T104: 0.3 | U104: 0.3 | V104: 0.3
A105: Маркетинг запуска (школы, вузы, родители, SMM) | B105: млн ₽ | C105: 0 | D105: 0 | E105: 2 | F105: 8 | G105: 0 | H105: 0 | I105: 0 | J105: 0 | K105: 0 | L105: 0 | M105: 0 | N105: 0 | O105: 0 | P105: 0 | Q105: 0 | R105: 0 | S105: 0 | T105: 0 | U105: 0 | V105: 0
A106: Текущий маркетинг и партнёрства | B106: млн ₽ | C106: 0 | D106: 0 | E106: 0 | F106: 0 | G106: 2 | H106: 2 | I106: 2 | J106: 2 | K106: 2 | L106: 2 | M106: 2 | N106: 2 | O106: 2 | P106: 2 | Q106: 2 | R106: 2 | S106: 2 | T106: 2 | U106: 2 | V106: 2
A107: Этап 2: доработка и поддержка перехвата для клиентов 23+ | B107: млн ₽ | C107: 0 | D107: 0 | E107: 0 | F107: 0 | G107: 3 | H107: 3 | I107: 2 | J107: 2 | K107: 2 | L107: 2 | M107: 2 | N107: 2 | O107: 2 | P107: 2 | Q107: 2 | R107: 2 | S107: 2 | T107: 2 | U107: 2 | V107: 2
A108: Мост «Детский банк» → «Старт»: интеграция и поддержка | B108: млн ₽ | C108: 0 | D108: 2 | E108: 1 | F108: 0 | G108: 0.25 | H108: 0.25 | I108: 0.25 | J108: 0.25 | K108: 0.25 | L108: 0.25 | M108: 0.25 | N108: 0.25 | O108: 0.25 | P108: 0.25 | Q108: 0.25 | R108: 0.25 | S108: 0.25 | T108: 0.25 | U108: 0.25 | V108: 0.25
A109: «Пушкинская карта» → «Старт»: витрина и онбординг | B109: млн ₽ | C109: 0 | D109: 0 | E109: 1.5 | F109: 0.5 | G109: 0.25 | H109: 0.25 | I109: 0.25 | J109: 0.25 | K109: 0.25 | L109: 0.25 | M109: 0.25 | N109: 0.25 | O109: 0.25 | P109: 0.25 | Q109: 0.25 | R109: 0.25 | S109: 0.25 | T109: 0.25 | U109: 0.25 | V109: 0.25

Sheet Расчёт_П
A1: Расчёт: Пессимистичный сценарий
A2: Все значения — формулы от листа «Допущения» (колонка сценария). Деньги — млн ₽.
A4: Аудитория и базовые величины
A5: Молодёжь 14–17 лет в РФ | B5: тыс. чел. | C5: ='Допущения'!$C$8*'Допущения'!$C$9
A6: Молодёжь 18–22 лет в РФ | B6: тыс. чел. | C6: ='Допущения'!$C$7*'Допущения'!$C$9
A7: TAM: вся молодёжь 14–22 | B7: тыс. чел. | C7: =C5+C6
A8: SAM: молодёжь 14–22 с банковской картой | B8: тыс. чел. | C8: =C5*'Допущения'!$C$10+C6*'Допущения'!$C$11
A9: SOM: клиенты ВТБ 14–22 | B9: тыс. чел. | C9: =C5*'Допущения'!$C$10*'Допущения'!$C$12+C6*'Допущения'!$C$11*'Допущения'!$C$13
A10: Проверка: клиенты ВТБ 14–25 по модели (факт ВТБ — на листе «Допущения») | B10: тыс. чел. | C10: =C9+'Допущения'!$C$16*'Допущения'!$C$9*'Допущения'!$C$11*'Допущения'!$C$13
A11: Дропов 14–22 лет в РФ в год | B11: тыс. чел. | C11: ='Допущения'!$C$14*12*'Допущения'!$C$15/1000
A12: Вероятность стать дропом за год для молодого клиента с картой | B12: доля | C12: =IF(C8>0,C11/C8,0)
A13: Дроп-кейсов среди клиентов ВТБ 14–22 в год (без продукта) | B13: шт. | C13: =C9*1000*C12
A14: Маржинальный доход на молодого клиента | B14: ₽/год | C14: ='Допущения'!$C$20*12*'Допущения'!$C$21+'Допущения'!$C$22*'Допущения'!$C$23-'Допущения'!$C$24
A15: Затраты банка на один дроп-кейс | B15: ₽ | C15: ='Допущения'!$C$28*'Допущения'!$C$29+'Допущения'!$C$30*'Допущения'!$C$31+'Допущения'!$C$32*'Допущения'!$C$33+'Допущения'!$C$34
A16: Квартальная ставка дисконтирования | B16: доля | C16: =(1+'Допущения'!$C$81)^(1/4)-1
A17: Полная стоимость сотрудника к зарплате (взносы + накладные) | B17: x | C17: =(1+'Допущения'!$C$76)*(1+'Допущения'!$C$77)
A18: Этап 2: дроп-кейсов среди клиентов ВТБ 23+ в год (без продукта) | B18: шт. | C18: ='Допущения'!$C$14*12*'Допущения'!$C$50*'Допущения'!$C$51
A19: Ценность будущего взрослого клиента на сегодня (на одного молодого клиента) | B19: ₽ | C19: ='Допущения'!$C$57*'Допущения'!$C$53*(1-(1+'Допущения'!$C$81)^(-'Допущения'!$C$59))/'Допущения'!$C$81/(1+'Допущения'!$C$81)^'Допущения'!$C$58
A20: Мост: дополнительно остаются в ВТБ при переходе в 14 лет | B20: чел./год | C20: ='Допущения'!$C$63*'Допущения'!$C$64*'Допущения'!$C$65*'Допущения'!$C$62
A21: Пушкинская карта: новых клиентов через «Старт» | B21: чел./год | C21: ='Допущения'!$C$67*'Допущения'!$C$68*'Допущения'!$C$69*'Допущения'!$C$66
A23: Показатель | B23: Ед. | C23: Q1 2027 | D23: Q2 2027 | E23: Q3 2027 | F23: Q4 2027 | G23: Q1 2028 | H23: Q2 2028 | I23: Q3 2028 | J23: Q4 2028 | K23: Q1 2029 | L23: Q2 2029 | M23: Q3 2029 | N23: Q4 2029 | O23: Q1 2030 | P23: Q2 2030 | Q23: Q3 2030 | R23: Q4 2030 | S23: Q1 2031 | T23: Q2 2031 | U23: Q3 2031 | V23: Q4 2031 | X23: 2027 | Y23: 2028 | Z23: 2029 | AA23: 2030 | AB23: 2031 | AC23: Итого
A24: Номер квартала | B24: № | C24: =1 | D24: =C24+1 | E24: =D24+1 | F24: =E24+1 | G24: =F24+1 | H24: =G24+1 | I24: =H24+1 | J24: =I24+1 | K24: =J24+1 | ... V24: =U24+1
A25: Флаг: разработка и пилот (полная команда) | B25: 0/1 | C25: =IF(C24<='Допущения'!$C$74,1,0) | D25: =IF(D24<='Допущения'!$C$74,1,0) | E25: =IF(E24<='Допущения'!$C$74,1,0) | F25: =IF(F24<='Допущения'!$C$74,1,0) | G25: =IF(G24<='Допущения'!$C$74,1,0) | H25: =IF(H24<='Допущения'!$C$74,1,0) | I25: =IF(I24<='Допущения'!$C$74,1,0) | J25: =IF(J24<='Допущения'!$C$74,1,0) | ... V25: =IF(V24<='Допущения'!$C$74,1,0)
A26: Флаг: продукт запущен для всех | B26: 0/1 | C26: =IF(C24>='Допущения'!$C$75,1,0) | D26: =IF(D24>='Допущения'!$C$75,1,0) | E26: =IF(E24>='Допущения'!$C$75,1,0) | F26: =IF(F24>='Допущения'!$C$75,1,0) | G26: =IF(G24>='Допущения'!$C$75,1,0) | H26: =IF(H24>='Допущения'!$C$75,1,0) | I26: =IF(I24>='Допущения'!$C$75,1,0) | J26: =IF(J24>='Допущения'!$C$75,1,0) | ... V26: =IF(V24>='Допущения'!$C$75,1,0)
A27: Покрытие перехватом (доля молодых клиентов) | B27: доля | C27: ='Допущения'!C$100 | D27: ='Допущения'!D$100 | E27: ='Допущения'!E$100 | F27: ='Допущения'!F$100 | G27: ='Допущения'!G$100 | H27: ='Допущения'!H$100 | I27: ='Допущения'!I$100 | J27: ='Допущения'!J$100 | ... V27: ='Допущения'!V$100 | X27: =F27 | Y27: =J27 | Z27: =N27 | AA27: =R27 | AB27: =V27 | AC27: =V27
A28: Флаг: этап 2 (перехват для клиентов 23+) | B28: 0/1 | C28: =IF(C24>='Допущения'!$C$49,1,0)*'Допущения'!$C$48 | D28: =IF(D24>='Допущения'!$C$49,1,0)*'Допущения'!$C$48 | E28: =IF(E24>='Допущения'!$C$49,1,0)*'Допущения'!$C$48 | F28: =IF(F24>='Допущения'!$C$49,1,0)*'Допущения'!$C$48 | G28: =IF(G24>='Допущения'!$C$49,1,0)*'Допущения'!$C$48 | H28: =IF(H24>='Допущения'!$C$49,1,0)*'Допущения'!$C$48 | I28: =IF(I24>='Допущения'!$C$49,1,0)*'Допущения'!$C$48 | J28: =IF(J24>='Допущения'!$C$49,1,0)*'Допущения'!$C$48 | ... V28: =IF(V24>='Допущения'!$C$49,1,0)*'Допущения'!$C$48
A29: Охват раздела «Старт»
A30: Доля молодых клиентов ВТБ — MAU раздела | B30: доля | C30: =MIN('Допущения'!$C$73,'Допущения'!C$99*'Допущения'!$C$72) | D30: =MIN('Допущения'!$C$73,'Допущения'!D$99*'Допущения'!$C$72) | E30: =MIN('Допущения'!$C$73,'Допущения'!E$99*'Допущения'!$C$72) | F30: =MIN('Допущения'!$C$73,'Допущения'!F$99*'Допущения'!$C$72) | G30: =MIN('Допущения'!$C$73,'Допущения'!G$99*'Допущения'!$C$72) | H30: =MIN('Допущения'!$C$73,'Допущения'!H$99*'Допущения'!$C$72) | I30: =MIN('Допущения'!$C$73,'Допущения'!I$99*'Допущения'!$C$72) | J30: =MIN('Допущения'!$C$73,'Допущения'!J$99*'Допущения'!$C$72) | ... V30: =MIN('Допущения'!$C$73,'Допущения'!V$99*'Допущения'!$C$72) | X30: =F30 | Y30: =J30 | Z30: =N30 | AA30: =R30 | AB30: =V30 | AC30: =V30
A31: MAU раздела «Старт» | B31: тыс. чел. | C31: =$C$9*C30 | D31: =$C$9*D30 | E31: =$C$9*E30 | F31: =$C$9*F30 | G31: =$C$9*G30 | H31: =$C$9*H30 | I31: =$C$9*I30 | J31: =$C$9*J30 | ... V31: =$C$9*V30 | X31: =F31 | Y31: =J31 | Z31: =N31 | AA31: =R31 | AB31: =V31 | AC31: =V31
A32: Эффект для банка — молодёжь 14–22
A33: Предотвращённые дроп-кейсы (перехват у всех + уроки у MAU) | B33: шт. | C33: =$C$9*1000*$C$12/4*(C27*'Допущения'!$C$39+C30*'Допущения'!$C$40) | D33: =$C$9*1000*$C$12/4*(D27*'Допущения'!$C$39+D30*'Допущения'!$C$40) | E33: =$C$9*1000*$C$12/4*(E27*'Допущения'!$C$39+E30*'Допущения'!$C$40) | F33: =$C$9*1000*$C$12/4*(F27*'Допущения'!$C$39+F30*'Допущения'!$C$40) | G33: =$C$9*1000*$C$12/4*(G27*'Допущения'!$C$39+G30*'Допущения'!$C$40) | H33: =$C$9*1000*$C$12/4*(H27*'Допущения'!$C$39+H30*'Допущения'!$C$40) | I33: =$C$9*1000*$C$12/4*(I27*'Допущения'!$C$39+I30*'Допущения'!$C$40) | J33: =$C$9*1000*$C$12/4*(J27*'Допущения'!$C$39+J30*'Допущения'!$C$40) | ... V33: =$C$9*1000*$C$12/4*(V27*'Допущения'!$C$39+V30*'Допущения'!$C$40) | X33: =SUM(C33:F33) | Y33: =SUM(G33:J33) | Z33: =SUM(K33:N33) | AA33: =SUM(O33:R33) | AB33: =SUM(S33:V33) | AC33: =SUM(C33:V33)
A34: 1. Экономия на разборе дроп-кейсов | B34: млн ₽ | C34: =C33*$C$15/1000000 | D34: =D33*$C$15/1000000 | E34: =E33*$C$15/1000000 | F34: =F33*$C$15/1000000 | G34: =G33*$C$15/1000000 | H34: =H33*$C$15/1000000 | I34: =I33*$C$15/1000000 | J34: =J33*$C$15/1000000 | ... V34: =V33*$C$15/1000000 | X34: =SUM(C34:F34) | Y34: =SUM(G34:J34) | Z34: =SUM(K34:N34) | AA34: =SUM(O34:R34) | AB34: =SUM(S34:V34) | AC34: =SUM(C34:V34)
A35: Сохранённые клиенты (не потеряны из-за дропа), накопительно | B35: чел. | C35: =C33*'Допущения'!$C$35 | D35: =C35*(1-'Допущения'!$C$25/4)+D33*'Допущения'!$C$35 | E35: =D35*(1-'Допущения'!$C$25/4)+E33*'Допущения'!$C$35 | F35: =E35*(1-'Допущения'!$C$25/4)+F33*'Допущения'!$C$35 | G35: =F35*(1-'Допущения'!$C$25/4)+G33*'Допущения'!$C$35 | H35: =G35*(1-'Допущения'!$C$25/4)+H33*'Допущения'!$C$35 | I35: =H35*(1-'Допущения'!$C$25/4)+I33*'Допущения'!$C$35 | J35: =I35*(1-'Допущения'!$C$25/4)+J33*'Допущения'!$C$35 | K35: =J35*(1-'Допущения'!$C$25/4)+K33*'Допущения'!$C$35 | ... V35: =U35*(1-'Допущения'!$C$25/4)+V33*'Допущения'!$C$35 | X35: =F35 | Y35: =J35 | Z35: =N35 | AA35: =R35 | AB35: =V35 | AC35: =V35
A36: 2. Доход от сохранённых клиентов | B36: млн ₽ | C36: =C35*$C$14/4/1000000 | D36: =D35*$C$14/4/1000000 | E36: =E35*$C$14/4/1000000 | F36: =F35*$C$14/4/1000000 | G36: =G35*$C$14/4/1000000 | H36: =H35*$C$14/4/1000000 | I36: =I35*$C$14/4/1000000 | J36: =J35*$C$14/4/1000000 | ... V36: =V35*$C$14/4/1000000 | X36: =SUM(C36:F36) | Y36: =SUM(G36:J36) | Z36: =SUM(K36:N36) | AA36: =SUM(O36:R36) | AB36: =SUM(S36:V36) | AC36: =SUM(C36:V36)
A37: Дополнительно удержанные пользователи раздела, накопительно | B37: чел. | C37: =C31*1000*'Допущения'!$C$41/4 | D37: =C37*(1-'Допущения'!$C$25/4)+D31*1000*'Допущения'!$C$41/4 | E37: =D37*(1-'Допущения'!$C$25/4)+E31*1000*'Допущения'!$C$41/4 | F37: =E37*(1-'Допущения'!$C$25/4)+F31*1000*'Допущения'!$C$41/4 | G37: =F37*(1-'Допущения'!$C$25/4)+G31*1000*'Допущения'!$C$41/4 | H37: =G37*(1-'Допущения'!$C$25/4)+H31*1000*'Допущения'!$C$41/4 | I37: =H37*(1-'Допущения'!$C$25/4)+I31*1000*'Допущения'!$C$41/4 | J37: =I37*(1-'Допущения'!$C$25/4)+J31*1000*'Допущения'!$C$41/4 | K37: =J37*(1-'Допущения'!$C$25/4)+K31*1000*'Допущения'!$C$41/4 | ... V37: =U37*(1-'Допущения'!$C$25/4)+V31*1000*'Допущения'!$C$41/4 | X37: =F37 | Y37: =J37 | Z37: =N37 | AA37: =R37 | AB37: =V37 | AC37: =V37
A38: 3. Доход от снижения оттока | B38: млн ₽ | C38: =C37*$C$14/4/1000000 | D38: =D37*$C$14/4/1000000 | E38: =E37*$C$14/4/1000000 | F38: =F37*$C$14/4/1000000 | G38: =G37*$C$14/4/1000000 | H38: =H37*$C$14/4/1000000 | I38: =I37*$C$14/4/1000000 | J38: =J37*$C$14/4/1000000 | ... V38: =V37*$C$14/4/1000000 | X38: =SUM(C38:F38) | Y38: =SUM(G38:J38) | Z38: =SUM(K38:N38) | AA38: =SUM(O38:R38) | AB38: =SUM(S38:V38) | AC38: =SUM(C38:V38)
A39: Новые клиенты благодаря продукту, накопительно | B39: чел. | C39: ='Допущения'!$C$44/4*'Допущения'!$C$45*C26 | D39: =C39*(1-'Допущения'!$C$25/4)+'Допущения'!$C$44/4*'Допущения'!$C$45*D26 | E39: =D39*(1-'Допущения'!$C$25/4)+'Допущения'!$C$44/4*'Допущения'!$C$45*E26 | F39: =E39*(1-'Допущения'!$C$25/4)+'Допущения'!$C$44/4*'Допущения'!$C$45*F26 | G39: =F39*(1-'Допущения'!$C$25/4)+'Допущения'!$C$44/4*'Допущения'!$C$45*G26 | H39: =G39*(1-'Допущения'!$C$25/4)+'Допущения'!$C$44/4*'Допущения'!$C$45*H26 | I39: =H39*(1-'Допущения'!$C$25/4)+'Допущения'!$C$44/4*'Допущения'!$C$45*I26 | J39: =I39*(1-'Допущения'!$C$25/4)+'Допущения'!$C$44/4*'Допущения'!$C$45*J26 | K39: =J39*(1-'Допущения'!$C$25/4)+'Допущения'!$C$44/4*'Допущения'!$C$45*K26 | ... V39: =U39*(1-'Допущения'!$C$25/4)+'Допущения'!$C$44/4*'Допущения'!$C$45*V26 | X39: =F39 | Y39: =J39 | Z39: =N39 | AA39: =R39 | AB39: =V39 | AC39: =V39
A40: 4. Доход от новых клиентов | B40: млн ₽ | C40: =C39*$C$14/4/1000000 | D40: =D39*$C$14/4/1000000 | E40: =E39*$C$14/4/1000000 | F40: =F39*$C$14/4/1000000 | G40: =G39*$C$14/4/1000000 | H40: =H39*$C$14/4/1000000 | I40: =I39*$C$14/4/1000000 | J40: =J39*$C$14/4/1000000 | ... V40: =V39*$C$14/4/1000000 | X40: =SUM(C40:F40) | Y40: =SUM(G40:J40) | Z40: =SUM(K40:N40) | AA40: =SUM(O40:R40) | AB40: =SUM(S40:V40) | AC40: =SUM(C40:V40)
A41: Обращения в КЦ, закрытые самообслуживанием | B41: шт. | C41: =$C$9*1000*'Допущения'!$C$42/4*'Допущения'!$C$43*C27 | D41: =$C$9*1000*'Допущения'!$C$42/4*'Допущения'!$C$43*D27 | E41: =$C$9*1000*'Допущения'!$C$42/4*'Допущения'!$C$43*E27 | F41: =$C$9*1000*'Допущения'!$C$42/4*'Допущения'!$C$43*F27 | G41: =$C$9*1000*'Допущения'!$C$42/4*'Допущения'!$C$43*G27 | H41: =$C$9*1000*'Допущения'!$C$42/4*'Допущения'!$C$43*H27 | I41: =$C$9*1000*'Допущения'!$C$42/4*'Допущения'!$C$43*I27 | J41: =$C$9*1000*'Допущения'!$C$42/4*'Допущения'!$C$43*J27 | ... V41: =$C$9*1000*'Допущения'!$C$42/4*'Допущения'!$C$43*V27 | X41: =SUM(C41:F41) | Y41: =SUM(G41:J41) | Z41: =SUM(K41:N41) | AA41: =SUM(O41:R41) | AB41: =SUM(S41:V41) | AC41: =SUM(C41:V41)
A42: 5. Экономия контакт-центра | B42: млн ₽ | C42: =C41*'Допущения'!$C$31/1000000 | D42: =D41*'Допущения'!$C$31/1000000 | E42: =E41*'Допущения'!$C$31/1000000 | F42: =F41*'Допущения'!$C$31/1000000 | G42: =G41*'Допущения'!$C$31/1000000 | H42: =H41*'Допущения'!$C$31/1000000 | I42: =I41*'Допущения'!$C$31/1000000 | J42: =J41*'Допущения'!$C$31/1000000 | ... V42: =V41*'Допущения'!$C$31/1000000 | X42: =SUM(C42:F42) | Y42: =SUM(G42:J42) | Z42: =SUM(K42:N42) | AA42: =SUM(O42:R42) | AB42: =SUM(S42:V42) | AC42: =SUM(C42:V42)
A43: Эффект для банка — мост из «Детского банка» и «Пушкинская карта»
A44: Мост 14 лет: дополнительно оставшиеся подростки, накопительно | B44: чел. | C44: =$C$20/4*C26 | D44: =C44*(1-'Допущения'!$C$25/4)+$C$20/4*D26 | E44: =D44*(1-'Допущения'!$C$25/4)+$C$20/4*E26 | F44: =E44*(1-'Допущения'!$C$25/4)+$C$20/4*F26 | G44: =F44*(1-'Допущения'!$C$25/4)+$C$20/4*G26 | H44: =G44*(1-'Допущения'!$C$25/4)+$C$20/4*H26 | I44: =H44*(1-'Допущения'!$C$25/4)+$C$20/4*I26 | J44: =I44*(1-'Допущения'!$C$25/4)+$C$20/4*J26 | K44: =J44*(1-'Допущения'!$C$25/4)+$C$20/4*K26 | ... V44: =U44*(1-'Допущения'!$C$25/4)+$C$20/4*V26 | X44: =F44 | Y44: =J44 | Z44: =N44 | AA44: =R44 | AB44: =V44 | AC44: =V44
A45: 8. Доход от моста «Детский банк» → «Старт» | B45: млн ₽ | C45: =C44*$C$14/4/1000000 | D45: =D44*$C$14/4/1000000 | E45: =E44*$C$14/4/1000000 | F45: =F44*$C$14/4/1000000 | G45: =G44*$C$14/4/1000000 | H45: =H44*$C$14/4/1000000 | I45: =I44*$C$14/4/1000000 | J45: =J44*$C$14/4/1000000 | ... V45: =V44*$C$14/4/1000000 | X45: =SUM(C45:F45) | Y45: =SUM(G45:J45) | Z45: =SUM(K45:N45) | AA45: =SUM(O45:R45) | AB45: =SUM(S45:V45) | AC45: =SUM(C45:V45)
A46: Пушкинская карта: новые клиенты через «Старт», накопительно | B46: чел. | C46: =$C$21/4*C26 | D46: =C46*(1-'Допущения'!$C$25/4)+$C$21/4*D26 | E46: =D46*(1-'Допущения'!$C$25/4)+$C$21/4*E26 | F46: =E46*(1-'Допущения'!$C$25/4)+$C$21/4*F26 | G46: =F46*(1-'Допущения'!$C$25/4)+$C$21/4*G26 | H46: =G46*(1-'Допущения'!$C$25/4)+$C$21/4*H26 | I46: =H46*(1-'Допущения'!$C$25/4)+$C$21/4*I26 | J46: =I46*(1-'Допущения'!$C$25/4)+$C$21/4*J26 | K46: =J46*(1-'Допущения'!$C$25/4)+$C$21/4*K26 | ... V46: =U46*(1-'Допущения'!$C$25/4)+$C$21/4*V26 | X46: =F46 | Y46: =J46 | Z46: =N46 | AA46: =R46 | AB46: =V46 | AC46: =V46
A47: 9. Доход от клиентов из «Пушкинской карты» | B47: млн ₽ | C47: =C46*$C$14/4/1000000 | D47: =D46*$C$14/4/1000000 | E47: =E46*$C$14/4/1000000 | F47: =F46*$C$14/4/1000000 | G47: =G46*$C$14/4/1000000 | H47: =H46*$C$14/4/1000000 | I47: =I46*$C$14/4/1000000 | J47: =J46*$C$14/4/1000000 | ... V47: =V46*$C$14/4/1000000 | X47: =SUM(C47:F47) | Y47: =SUM(G47:J47) | Z47: =SUM(K47:N47) | AA47: =SUM(O47:R47) | AB47: =SUM(S47:V47) | AC47: =SUM(C47:V47)
A48: Эффект для банка — этап 2: перехват для клиентов 23+
A49: Предотвращённые дроп-кейсы 23+ | B49: шт. | C49: =$C$18/4*'Допущения'!$C$52*C28 | D49: =$C$18/4*'Допущения'!$C$52*D28 | E49: =$C$18/4*'Допущения'!$C$52*E28 | F49: =$C$18/4*'Допущения'!$C$52*F28 | G49: =$C$18/4*'Допущения'!$C$52*G28 | H49: =$C$18/4*'Допущения'!$C$52*H28 | I49: =$C$18/4*'Допущения'!$C$52*I28 | J49: =$C$18/4*'Допущения'!$C$52*J28 | ... V49: =$C$18/4*'Допущения'!$C$52*V28 | X49: =SUM(C49:F49) | Y49: =SUM(G49:J49) | Z49: =SUM(K49:N49) | AA49: =SUM(O49:R49) | AB49: =SUM(S49:V49) | AC49: =SUM(C49:V49)
A50: 6. Экономия на разборе дроп-кейсов 23+ | B50: млн ₽ | C50: =C49*$C$15/1000000 | D50: =D49*$C$15/1000000 | E50: =E49*$C$15/1000000 | F50: =F49*$C$15/1000000 | G50: =G49*$C$15/1000000 | H50: =H49*$C$15/1000000 | I50: =I49*$C$15/1000000 | J50: =J49*$C$15/1000000 | ... V50: =V49*$C$15/1000000 | X50: =SUM(C50:F50) | Y50: =SUM(G50:J50) | Z50: =SUM(K50:N50) | AA50: =SUM(O50:R50) | AB50: =SUM(S50:V50) | AC50: =SUM(C50:V50)
A51: Сохранённые взрослые клиенты, накопительно | B51: чел. | C51: =C49*'Допущения'!$C$35 | D51: =C51*(1-'Допущения'!$C$54/4)+D49*'Допущения'!$C$35 | E51: =D51*(1-'Допущения'!$C$54/4)+E49*'Допущения'!$C$35 | F51: =E51*(1-'Допущения'!$C$54/4)+F49*'Допущения'!$C$35 | G51: =F51*(1-'Допущения'!$C$54/4)+G49*'Допущения'!$C$35 | H51: =G51*(1-'Допущения'!$C$54/4)+H49*'Допущения'!$C$35 | I51: =H51*(1-'Допущения'!$C$54/4)+I49*'Допущения'!$C$35 | J51: =I51*(1-'Допущения'!$C$54/4)+J49*'Допущения'!$C$35 | K51: =J51*(1-'Допущения'!$C$54/4)+K49*'Допущения'!$C$35 | ... V51: =U51*(1-'Допущения'!$C$54/4)+V49*'Допущения'!$C$35 | X51: =F51 | Y51: =J51 | Z51: =N51 | AA51: =R51 | AB51: =V51 | AC51: =V51
A52: 7. Доход от сохранённых взрослых клиентов | B52: млн ₽ | C52: =C51*'Допущения'!$C$53/4/1000000 | D52: =D51*'Допущения'!$C$53/4/1000000 | E52: =E51*'Допущения'!$C$53/4/1000000 | F52: =F51*'Допущения'!$C$53/4/1000000 | G52: =G51*'Допущения'!$C$53/4/1000000 | H52: =H51*'Допущения'!$C$53/4/1000000 | I52: =I51*'Допущения'!$C$53/4/1000000 | J52: =J51*'Допущения'!$C$53/4/1000000 | ... V52: =V51*'Допущения'!$C$53/4/1000000 | X52: =SUM(C52:F52) | Y52: =SUM(G52:J52) | Z52: =SUM(K52:N52) | AA52: =SUM(O52:R52) | AB52: =SUM(S52:V52) | AC52: =SUM(C52:V52)
A53: ИТОГО ЭФФЕКТ | B53: млн ₽ | C53: =C34+C36+C38+C40+C42+C45+C47+C50+C52 | D53: =D34+D36+D38+D40+D42+D45+D47+D50+D52 | E53: =E34+E36+E38+E40+E42+E45+E47+E50+E52 | F53: =F34+F36+F38+F40+F42+F45+F47+F50+F52 | G53: =G34+G36+G38+G40+G42+G45+G47+G50+G52 | H53: =H34+H36+H38+H40+H42+H45+H47+H50+H52 | I53: =I34+I36+I38+I40+I42+I45+I47+I50+I52 | J53: =J34+J36+J38+J40+J42+J45+J47+J50+J52 | ... V53: =V34+V36+V38+V40+V42+V45+V47+V50+V52 | X53: =SUM(C53:F53) | Y53: =SUM(G53:J53) | Z53: =SUM(K53:N53) | AA53: =SUM(O53:R53) | AB53: =SUM(S53:V53) | AC53: =SUM(C53:V53)
A54: Затраты на внедрение и поддержку
A55: Команда: разработка и пилот | B55: млн ₽ | C55: =C25*SUMPRODUCT('Допущения'!$C$85:$C$93,'Допущения'!$B$85:$B$93)*1000*$C$17*3/1000000 | D55: =D25*SUMPRODUCT('Допущения'!$C$85:$C$93,'Допущения'!$B$85:$B$93)*1000*$C$17*3/1000000 | E55: =E25*SUMPRODUCT('Допущения'!$C$85:$C$93,'Допущения'!$B$85:$B$93)*1000*$C$17*3/1000000 | F55: =F25*SUMPRODUCT('Допущения'!$C$85:$C$93,'Допущения'!$B$85:$B$93)*1000*$C$17*3/1000000 | G55: =G25*SUMPRODUCT('Допущения'!$C$85:$C$93,'Допущения'!$B$85:$B$93)*1000*$C$17*3/1000000 | H55: =H25*SUMPRODUCT('Допущения'!$C$85:$C$93,'Допущения'!$B$85:$B$93)*1000*$C$17*3/1000000 | I55: =I25*SUMPRODUCT('Допущения'!$C$85:$C$93,'Допущения'!$B$85:$B$93)*1000*$C$17*3/1000000 | J55: =J25*SUMPRODUCT('Допущения'!$C$85:$C$93,'Допущения'!$B$85:$B$93)*1000*$C$17*3/1000000 | ... V55: =V25*SUMPRODUCT('Допущения'!$C$85:$C$93,'Допущения'!$B$85:$B$93)*1000*$C$17*3/1000000 | X55: =SUM(C55:F55) | Y55: =SUM(G55:J55) | Z55: =SUM(K55:N55) | AA55: =SUM(O55:R55) | AB55: =SUM(S55:V55) | AC55: =SUM(C55:V55)
A56: Команда: эксплуатация и развитие | B56: млн ₽ | C56: =(1-C25)*SUMPRODUCT('Допущения'!$D$85:$D$93,'Допущения'!$B$85:$B$93)*1000*$C$17*3/1000000 | D56: =(1-D25)*SUMPRODUCT('Допущения'!$D$85:$D$93,'Допущения'!$B$85:$B$93)*1000*$C$17*3/1000000 | E56: =(1-E25)*SUMPRODUCT('Допущения'!$D$85:$D$93,'Допущения'!$B$85:$B$93)*1000*$C$17*3/1000000 | F56: =(1-F25)*SUMPRODUCT('Допущения'!$D$85:$D$93,'Допущения'!$B$85:$B$93)*1000*$C$17*3/1000000 | G56: =(1-G25)*SUMPRODUCT('Допущения'!$D$85:$D$93,'Допущения'!$B$85:$B$93)*1000*$C$17*3/1000000 | H56: =(1-H25)*SUMPRODUCT('Допущения'!$D$85:$D$93,'Допущения'!$B$85:$B$93)*1000*$C$17*3/1000000 | I56: =(1-I25)*SUMPRODUCT('Допущения'!$D$85:$D$93,'Допущения'!$B$85:$B$93)*1000*$C$17*3/1000000 | J56: =(1-J25)*SUMPRODUCT('Допущения'!$D$85:$D$93,'Допущения'!$B$85:$B$93)*1000*$C$17*3/1000000 | ... V56: =(1-V25)*SUMPRODUCT('Допущения'!$D$85:$D$93,'Допущения'!$B$85:$B$93)*1000*$C$17*3/1000000 | X56: =SUM(C56:F56) | Y56: =SUM(G56:J56) | Z56: =SUM(K56:N56) | AA56: =SUM(O56:R56) | AB56: =SUM(S56:V56) | AC56: =SUM(C56:V56)
A57: Инфраструктура, ИБ, контент, маркетинг (график) | B57: млн ₽ | C57: =SUM('Допущения'!C$101:C$106) | D57: =SUM('Допущения'!D$101:D$106) | E57: =SUM('Допущения'!E$101:E$106) | F57: =SUM('Допущения'!F$101:F$106) | G57: =SUM('Допущения'!G$101:G$106) | H57: =SUM('Допущения'!H$101:H$106) | I57: =SUM('Допущения'!I$101:I$106) | J57: =SUM('Допущения'!J$101:J$106) | ... V57: =SUM('Допущения'!V$101:V$106) | X57: =SUM(C57:F57) | Y57: =SUM(G57:J57) | Z57: =SUM(K57:N57) | AA57: =SUM(O57:R57) | AB57: =SUM(S57:V57) | AC57: =SUM(C57:V57)
A58: Мост и «Пушкинская карта»: интеграция и поддержка | B58: млн ₽ | C58: ='Допущения'!C$108*'Допущения'!$C$62+'Допущения'!C$109*'Допущения'!$C$66 | D58: ='Допущения'!D$108*'Допущения'!$C$62+'Допущения'!D$109*'Допущения'!$C$66 | E58: ='Допущения'!E$108*'Допущения'!$C$62+'Допущения'!E$109*'Допущения'!$C$66 | F58: ='Допущения'!F$108*'Допущения'!$C$62+'Допущения'!F$109*'Допущения'!$C$66 | G58: ='Допущения'!G$108*'Допущения'!$C$62+'Допущения'!G$109*'Допущения'!$C$66 | H58: ='Допущения'!H$108*'Допущения'!$C$62+'Допущения'!H$109*'Допущения'!$C$66 | I58: ='Допущения'!I$108*'Допущения'!$C$62+'Допущения'!I$109*'Допущения'!$C$66 | J58: ='Допущения'!J$108*'Допущения'!$C$62+'Допущения'!J$109*'Допущения'!$C$66 | ... V58: ='Допущения'!V$108*'Допущения'!$C$62+'Допущения'!V$109*'Допущения'!$C$66 | X58: =SUM(C58:F58) | Y58: =SUM(G58:J58) | Z58: =SUM(K58:N58) | AA58: =SUM(O58:R58) | AB58: =SUM(S58:V58) | AC58: =SUM(C58:V58)
A59: Этап 2: доработка и поддержка для клиентов 23+ | B59: млн ₽ | C59: ='Допущения'!C$107*'Допущения'!$C$48 | D59: ='Допущения'!D$107*'Допущения'!$C$48 | E59: ='Допущения'!E$107*'Допущения'!$C$48 | F59: ='Допущения'!F$107*'Допущения'!$C$48 | G59: ='Допущения'!G$107*'Допущения'!$C$48 | H59: ='Допущения'!H$107*'Допущения'!$C$48 | I59: ='Допущения'!I$107*'Допущения'!$C$48 | J59: ='Допущения'!J$107*'Допущения'!$C$48 | ... V59: ='Допущения'!V$107*'Допущения'!$C$48 | X59: =SUM(C59:F59) | Y59: =SUM(G59:J59) | Z59: =SUM(K59:N59) | AA59: =SUM(O59:R59) | AB59: =SUM(S59:V59) | AC59: =SUM(C59:V59)
A60: Вознаграждения пользователям | B60: млн ₽ | C60: =C31*1000*'Допущения'!$C$78/4/1000000 | D60: =D31*1000*'Допущения'!$C$78/4/1000000 | E60: =E31*1000*'Допущения'!$C$78/4/1000000 | F60: =F31*1000*'Допущения'!$C$78/4/1000000 | G60: =G31*1000*'Допущения'!$C$78/4/1000000 | H60: =H31*1000*'Допущения'!$C$78/4/1000000 | I60: =I31*1000*'Допущения'!$C$78/4/1000000 | J60: =J31*1000*'Допущения'!$C$78/4/1000000 | ... V60: =V31*1000*'Допущения'!$C$78/4/1000000 | X60: =SUM(C60:F60) | Y60: =SUM(G60:J60) | Z60: =SUM(K60:N60) | AA60: =SUM(O60:R60) | AB60: =SUM(S60:V60) | AC60: =SUM(C60:V60)
A61: Резерв на непредвиденное | B61: млн ₽ | C61: =(C55+C56+C57+C58+C59+C60)*'Допущения'!$C$79 | D61: =(D55+D56+D57+D58+D59+D60)*'Допущения'!$C$79 | E61: =(E55+E56+E57+E58+E59+E60)*'Допущения'!$C$79 | F61: =(F55+F56+F57+F58+F59+F60)*'Допущения'!$C$79 | G61: =(G55+G56+G57+G58+G59+G60)*'Допущения'!$C$79 | H61: =(H55+H56+H57+H58+H59+H60)*'Допущения'!$C$79 | I61: =(I55+I56+I57+I58+I59+I60)*'Допущения'!$C$79 | J61: =(J55+J56+J57+J58+J59+J60)*'Допущения'!$C$79 | ... V61: =(V55+V56+V57+V58+V59+V60)*'Допущения'!$C$79 | X61: =SUM(C61:F61) | Y61: =SUM(G61:J61) | Z61: =SUM(K61:N61) | AA61: =SUM(O61:R61) | AB61: =SUM(S61:V61) | AC61: =SUM(C61:V61)
A62: ИТОГО ЗАТРАТЫ (с учётом перерасхода) | B62: млн ₽ | C62: =(C55+C56+C57+C58+C59+C60+C61)*'Допущения'!$C$80 | D62: =(D55+D56+D57+D58+D59+D60+D61)*'Допущения'!$C$80 | E62: =(E55+E56+E57+E58+E59+E60+E61)*'Допущения'!$C$80 | F62: =(F55+F56+F57+F58+F59+F60+F61)*'Допущения'!$C$80 | G62: =(G55+G56+G57+G58+G59+G60+G61)*'Допущения'!$C$80 | H62: =(H55+H56+H57+H58+H59+H60+H61)*'Допущения'!$C$80 | I62: =(I55+I56+I57+I58+I59+I60+I61)*'Допущения'!$C$80 | J62: =(J55+J56+J57+J58+J59+J60+J61)*'Допущения'!$C$80 | ... V62: =(V55+V56+V57+V58+V59+V60+V61)*'Допущения'!$C$80 | X62: =SUM(C62:F62) | Y62: =SUM(G62:J62) | Z62: =SUM(K62:N62) | AA62: =SUM(O62:R62) | AB62: =SUM(S62:V62) | AC62: =SUM(C62:V62)
A63: Денежный поток
A64: Чистый денежный поток | B64: млн ₽ | C64: =C53-C62 | D64: =D53-D62 | E64: =E53-E62 | F64: =F53-F62 | G64: =G53-G62 | H64: =H53-H62 | I64: =I53-I62 | J64: =J53-J62 | ... V64: =V53-V62 | X64: =SUM(C64:F64) | Y64: =SUM(G64:J64) | Z64: =SUM(K64:N64) | AA64: =SUM(O64:R64) | AB64: =SUM(S64:V64) | AC64: =SUM(C64:V64)
A65: Накопленный денежный поток | B65: млн ₽ | C65: =C64 | D65: =C65+D64 | E65: =D65+E64 | F65: =E65+F64 | G65: =F65+G64 | H65: =G65+H64 | I65: =H65+I64 | J65: =I65+J64 | K65: =J65+K64 | ... V65: =U65+V64 | X65: =F65 | Y65: =J65 | Z65: =N65 | AA65: =R65 | AB65: =V65 | AC65: =V65
A66: Коэффициент дисконтирования | B66: x | C66: =1/(1+$C$16)^C24 | D66: =1/(1+$C$16)^D24 | E66: =1/(1+$C$16)^E24 | F66: =1/(1+$C$16)^F24 | G66: =1/(1+$C$16)^G24 | H66: =1/(1+$C$16)^H24 | I66: =1/(1+$C$16)^I24 | J66: =1/(1+$C$16)^J24 | ... V66: =1/(1+$C$16)^V24
A67: Дисконтированный поток | B67: млн ₽ | C67: =C64*C66 | D67: =D64*D66 | E67: =E64*E66 | F67: =F64*F66 | G67: =G64*G66 | H67: =H64*H66 | I67: =I64*I66 | J67: =J64*J66 | ... V67: =V64*V66 | X67: =SUM(C67:F67) | Y67: =SUM(G67:J67) | Z67: =SUM(K67:N67) | AA67: =SUM(O67:R67) | AB67: =SUM(S67:V67) | AC67: =SUM(C67:V67)
A68: Служебная: номер квартала, если накопленный поток ≥ 0 | B68: № | C68: =IF(C65>=0,C24,99) | D68: =IF(D65>=0,D24,99) | E68: =IF(E65>=0,E24,99) | F68: =IF(F65>=0,F24,99) | G68: =IF(G65>=0,G24,99) | H68: =IF(H65>=0,H24,99) | I68: =IF(I65>=0,I24,99) | J68: =IF(J65>=0,J24,99) | ... V68: =IF(V65>=0,V24,99)
A69: Поток ядра продукта: без этапа 2, моста и «Пушкинской карты» | B69: млн ₽ | C69: =(C53-C50-C52-C45-C47)-(C55+C56+C57+C60)*(1+'Допущения'!$C$79)*'Допущения'!$C$80 | D69: =(D53-D50-D52-D45-D47)-(D55+D56+D57+D60)*(1+'Допущения'!$C$79)*'Допущения'!$C$80 | E69: =(E53-E50-E52-E45-E47)-(E55+E56+E57+E60)*(1+'Допущения'!$C$79)*'Допущения'!$C$80 | F69: =(F53-F50-F52-F45-F47)-(F55+F56+F57+F60)*(1+'Допущения'!$C$79)*'Допущения'!$C$80 | G69: =(G53-G50-G52-G45-G47)-(G55+G56+G57+G60)*(1+'Допущения'!$C$79)*'Допущения'!$C$80 | H69: =(H53-H50-H52-H45-H47)-(H55+H56+H57+H60)*(1+'Допущения'!$C$79)*'Допущения'!$C$80 | I69: =(I53-I50-I52-I45-I47)-(I55+I56+I57+I60)*(1+'Допущения'!$C$79)*'Допущения'!$C$80 | J69: =(J53-J50-J52-J45-J47)-(J55+J56+J57+J60)*(1+'Допущения'!$C$79)*'Допущения'!$C$80 | ... V69: =(V53-V50-V52-V45-V47)-(V55+V56+V57+V60)*(1+'Допущения'!$C$79)*'Допущения'!$C$80 | X69: =SUM(C69:F69) | Y69: =SUM(G69:J69) | Z69: =SUM(K69:N69) | AA69: =SUM(O69:R69) | AB69: =SUM(S69:V69) | AC69: =SUM(C69:V69)
A70: Итоговые показатели сценария
A71: NPV за 5 лет (2027–2031) | B71: млн ₽ | C71: =SUM(C67:V67)
A72: NPV за 5 лет только ядра продукта (без этапа 2, моста и «Пушкинской карты») | B72: млн ₽ | C72: =SUMPRODUCT(C69:V69,C66:V66)
A73: NPV за первые 3 года (2027–2029), справочно | B73: млн ₽ | C73: =SUM(C67:N67)
A74: Суммарный эффект за 5 лет | B74: млн ₽ | C74: =AC53
A75: Суммарные затраты за 5 лет | B75: млн ₽ | C75: =AC62
A76: ROI за 5 лет | B76: доля | C76: =IF(C75>0,(C74-C75)/C75,0)
A77: Инвестиции до полного запуска (разработка + пилот) | B77: млн ₽ | C77: =SUMPRODUCT(C62:V62,C25:V25)
A78: Квартал окупаемости (99 — не окупается за 5 лет) | B78: № | C78: =MIN(C68:V68)
A79: Срок окупаемости от старта проекта | B79: мес. | C79: =IF(C78=99,"больше 60",IF(C78=1,0,(C78-1)*3+3*(-INDEX(C65:V65,C78-1))/INDEX(C64:V64,C78)))
A80: Срок окупаемости от полного запуска | B80: мес. | C80: =IF(C78=99,"больше 60",C79-('Допущения'!$C$75-1)*3)
A81: Годовые затраты в режиме эксплуатации (2031) | B81: млн ₽ | C81: =AB62
A82: Годовой эффект (2031) | B82: млн ₽ | C82: =AB53
A83: Операционный поток 2029 (эффект минус затраты) | B83: млн ₽ | C83: =Z53-Z62
A84: Предотвращено дроп-кейсов молодёжи за 5 лет | B84: шт. | C84: =AC33
A85: Предотвращено дроп-кейсов 23+ за 5 лет | B85: шт. | C85: =AC49
A86: Социальный эффект: чужих денег не прошло через карты ВТБ (вне NPV) | B86: млн ₽ | C86: =(C84+C85)*'Допущения'!$C$36/1000000
A87: MAU раздела на конец 2031 | B87: тыс. чел. | C87: =V31
A88: Молодых клиентов сохранено, удержано и привлечено (на конец 2031) | B88: чел. | C88: =V35+V37+V39+V44+V46
A89: Стратегическая ценность этих клиентов после 23 лет (вне NPV) | B89: млн ₽ | C89: =C88*C19/1000000
A90: Затраты на одного MAU в 2031 | B90: ₽/год | C90: =IF(V31>0,AB62*1000000/(V31*1000),0)

Sheet Расчёт_Б
A1: Расчёт: Базовый сценарий
A2: Все значения — формулы от листа «Допущения» (колонка сценария). Деньги — млн ₽.
A4: Аудитория и базовые величины
A5: Молодёжь 14–17 лет в РФ | B5: тыс. чел. | C5: ='Допущения'!$D$8*'Допущения'!$D$9
A6: Молодёжь 18–22 лет в РФ | B6: тыс. чел. | C6: ='Допущения'!$D$7*'Допущения'!$D$9
A7: TAM: вся молодёжь 14–22 | B7: тыс. чел. | C7: =C5+C6
A8: SAM: молодёжь 14–22 с банковской картой | B8: тыс. чел. | C8: =C5*'Допущения'!$D$10+C6*'Допущения'!$D$11
A9: SOM: клиенты ВТБ 14–22 | B9: тыс. чел. | C9: =C5*'Допущения'!$D$10*'Допущения'!$D$12+C6*'Допущения'!$D$11*'Допущения'!$D$13
A10: Проверка: клиенты ВТБ 14–25 по модели (факт ВТБ — на листе «Допущения») | B10: тыс. чел. | C10: =C9+'Допущения'!$D$16*'Допущения'!$D$9*'Допущения'!$D$11*'Допущения'!$D$13
A11: Дропов 14–22 лет в РФ в год | B11: тыс. чел. | C11: ='Допущения'!$D$14*12*'Допущения'!$D$15/1000
A12: Вероятность стать дропом за год для молодого клиента с картой | B12: доля | C12: =IF(C8>0,C11/C8,0)
A13: Дроп-кейсов среди клиентов ВТБ 14–22 в год (без продукта) | B13: шт. | C13: =C9*1000*C12
A14: Маржинальный доход на молодого клиента | B14: ₽/год | C14: ='Допущения'!$D$20*12*'Допущения'!$D$21+'Допущения'!$D$22*'Допущения'!$D$23-'Допущения'!$D$24
A15: Затраты банка на один дроп-кейс | B15: ₽ | C15: ='Допущения'!$D$28*'Допущения'!$D$29+'Допущения'!$D$30*'Допущения'!$D$31+'Допущения'!$D$32*'Допущения'!$D$33+'Допущения'!$D$34
A16: Квартальная ставка дисконтирования | B16: доля | C16: =(1+'Допущения'!$D$81)^(1/4)-1
A17: Полная стоимость сотрудника к зарплате (взносы + накладные) | B17: x | C17: =(1+'Допущения'!$D$76)*(1+'Допущения'!$D$77)
A18: Этап 2: дроп-кейсов среди клиентов ВТБ 23+ в год (без продукта) | B18: шт. | C18: ='Допущения'!$D$14*12*'Допущения'!$D$50*'Допущения'!$D$51
A19: Ценность будущего взрослого клиента на сегодня (на одного молодого клиента) | B19: ₽ | C19: ='Допущения'!$D$57*'Допущения'!$D$53*(1-(1+'Допущения'!$D$81)^(-'Допущения'!$D$59))/'Допущения'!$D$81/(1+'Допущения'!$D$81)^'Допущения'!$D$58
A20: Мост: дополнительно остаются в ВТБ при переходе в 14 лет | B20: чел./год | C20: ='Допущения'!$D$63*'Допущения'!$D$64*'Допущения'!$D$65*'Допущения'!$D$62
A21: Пушкинская карта: новых клиентов через «Старт» | B21: чел./год | C21: ='Допущения'!$D$67*'Допущения'!$D$68*'Допущения'!$D$69*'Допущения'!$D$66
A23: Показатель | B23: Ед. | C23: Q1 2027 | D23: Q2 2027 | E23: Q3 2027 | F23: Q4 2027 | G23: Q1 2028 | H23: Q2 2028 | I23: Q3 2028 | J23: Q4 2028 | K23: Q1 2029 | L23: Q2 2029 | M23: Q3 2029 | N23: Q4 2029 | O23: Q1 2030 | P23: Q2 2030 | Q23: Q3 2030 | R23: Q4 2030 | S23: Q1 2031 | T23: Q2 2031 | U23: Q3 2031 | V23: Q4 2031 | X23: 2027 | Y23: 2028 | Z23: 2029 | AA23: 2030 | AB23: 2031 | AC23: Итого
A24: Номер квартала | B24: № | C24: =1 | D24: =C24+1 | E24: =D24+1 | F24: =E24+1 | G24: =F24+1 | H24: =G24+1 | I24: =H24+1 | J24: =I24+1 | K24: =J24+1 | ... V24: =U24+1
A25: Флаг: разработка и пилот (полная команда) | B25: 0/1 | C25: =IF(C24<='Допущения'!$D$74,1,0) | D25: =IF(D24<='Допущения'!$D$74,1,0) | E25: =IF(E24<='Допущения'!$D$74,1,0) | F25: =IF(F24<='Допущения'!$D$74,1,0) | G25: =IF(G24<='Допущения'!$D$74,1,0) | H25: =IF(H24<='Допущения'!$D$74,1,0) | I25: =IF(I24<='Допущения'!$D$74,1,0) | J25: =IF(J24<='Допущения'!$D$74,1,0) | ... V25: =IF(V24<='Допущения'!$D$74,1,0)
A26: Флаг: продукт запущен для всех | B26: 0/1 | C26: =IF(C24>='Допущения'!$D$75,1,0) | D26: =IF(D24>='Допущения'!$D$75,1,0) | E26: =IF(E24>='Допущения'!$D$75,1,0) | F26: =IF(F24>='Допущения'!$D$75,1,0) | G26: =IF(G24>='Допущения'!$D$75,1,0) | H26: =IF(H24>='Допущения'!$D$75,1,0) | I26: =IF(I24>='Допущения'!$D$75,1,0) | J26: =IF(J24>='Допущения'!$D$75,1,0) | ... V26: =IF(V24>='Допущения'!$D$75,1,0)
A27: Покрытие перехватом (доля молодых клиентов) | B27: доля | C27: ='Допущения'!C$100 | D27: ='Допущения'!D$100 | E27: ='Допущения'!E$100 | F27: ='Допущения'!F$100 | G27: ='Допущения'!G$100 | H27: ='Допущения'!H$100 | I27: ='Допущения'!I$100 | J27: ='Допущения'!J$100 | ... V27: ='Допущения'!V$100 | X27: =F27 | Y27: =J27 | Z27: =N27 | AA27: =R27 | AB27: =V27 | AC27: =V27
A28: Флаг: этап 2 (перехват для клиентов 23+) | B28: 0/1 | C28: =IF(C24>='Допущения'!$D$49,1,0)*'Допущения'!$D$48 | D28: =IF(D24>='Допущения'!$D$49,1,0)*'Допущения'!$D$48 | E28: =IF(E24>='Допущения'!$D$49,1,0)*'Допущения'!$D$48 | F28: =IF(F24>='Допущения'!$D$49,1,0)*'Допущения'!$D$48 | G28: =IF(G24>='Допущения'!$D$49,1,0)*'Допущения'!$D$48 | H28: =IF(H24>='Допущения'!$D$49,1,0)*'Допущения'!$D$48 | I28: =IF(I24>='Допущения'!$D$49,1,0)*'Допущения'!$D$48 | J28: =IF(J24>='Допущения'!$D$49,1,0)*'Допущения'!$D$48 | ... V28: =IF(V24>='Допущения'!$D$49,1,0)*'Допущения'!$D$48
A29: Охват раздела «Старт»
A30: Доля молодых клиентов ВТБ — MAU раздела | B30: доля | C30: =MIN('Допущения'!$D$73,'Допущения'!C$99*'Допущения'!$D$72) | D30: =MIN('Допущения'!$D$73,'Допущения'!D$99*'Допущения'!$D$72) | E30: =MIN('Допущения'!$D$73,'Допущения'!E$99*'Допущения'!$D$72) | F30: =MIN('Допущения'!$D$73,'Допущения'!F$99*'Допущения'!$D$72) | G30: =MIN('Допущения'!$D$73,'Допущения'!G$99*'Допущения'!$D$72) | H30: =MIN('Допущения'!$D$73,'Допущения'!H$99*'Допущения'!$D$72) | I30: =MIN('Допущения'!$D$73,'Допущения'!I$99*'Допущения'!$D$72) | J30: =MIN('Допущения'!$D$73,'Допущения'!J$99*'Допущения'!$D$72) | ... V30: =MIN('Допущения'!$D$73,'Допущения'!V$99*'Допущения'!$D$72) | X30: =F30 | Y30: =J30 | Z30: =N30 | AA30: =R30 | AB30: =V30 | AC30: =V30
A31: MAU раздела «Старт» | B31: тыс. чел. | C31: =$C$9*C30 | D31: =$C$9*D30 | E31: =$C$9*E30 | F31: =$C$9*F30 | G31: =$C$9*G30 | H31: =$C$9*H30 | I31: =$C$9*I30 | J31: =$C$9*J30 | ... V31: =$C$9*V30 | X31: =F31 | Y31: =J31 | Z31: =N31 | AA31: =R31 | AB31: =V31 | AC31: =V31
A32: Эффект для банка — молодёжь 14–22
A33: Предотвращённые дроп-кейсы (перехват у всех + уроки у MAU) | B33: шт. | C33: =$C$9*1000*$C$12/4*(C27*'Допущения'!$D$39+C30*'Допущения'!$D$40) | D33: =$C$9*1000*$C$12/4*(D27*'Допущения'!$D$39+D30*'Допущения'!$D$40) | E33: =$C$9*1000*$C$12/4*(E27*'Допущения'!$D$39+E30*'Допущения'!$D$40) | F33: =$C$9*1000*$C$12/4*(F27*'Допущения'!$D$39+F30*'Допущения'!$D$40) | G33: =$C$9*1000*$C$12/4*(G27*'Допущения'!$D$39+G30*'Допущения'!$D$40) | H33: =$C$9*1000*$C$12/4*(H27*'Допущения'!$D$39+H30*'Допущения'!$D$40) | I33: =$C$9*1000*$C$12/4*(I27*'Допущения'!$D$39+I30*'Допущения'!$D$40) | J33: =$C$9*1000*$C$12/4*(J27*'Допущения'!$D$39+J30*'Допущения'!$D$40) | ... V33: =$C$9*1000*$C$12/4*(V27*'Допущения'!$D$39+V30*'Допущения'!$D$40) | X33: =SUM(C33:F33) | Y33: =SUM(G33:J33) | Z33: =SUM(K33:N33) | AA33: =SUM(O33:R33) | AB33: =SUM(S33:V33) | AC33: =SUM(C33:V33)
A34: 1. Экономия на разборе дроп-кейсов | B34: млн ₽ | C34: =C33*$C$15/1000000 | D34: =D33*$C$15/1000000 | E34: =E33*$C$15/1000000 | F34: =F33*$C$15/1000000 | G34: =G33*$C$15/1000000 | H34: =H33*$C$15/1000000 | I34: =I33*$C$15/1000000 | J34: =J33*$C$15/1000000 | ... V34: =V33*$C$15/1000000 | X34: =SUM(C34:F34) | Y34: =SUM(G34:J34) | Z34: =SUM(K34:N34) | AA34: =SUM(O34:R34) | AB34: =SUM(S34:V34) | AC34: =SUM(C34:V34)
A35: Сохранённые клиенты (не потеряны из-за дропа), накопительно | B35: чел. | C35: =C33*'Допущения'!$D$35 | D35: =C35*(1-'Допущения'!$D$25/4)+D33*'Допущения'!$D$35 | E35: =D35*(1-'Допущения'!$D$25/4)+E33*'Допущения'!$D$35 | F35: =E35*(1-'Допущения'!$D$25/4)+F33*'Допущения'!$D$35 | G35: =F35*(1-'Допущения'!$D$25/4)+G33*'Допущения'!$D$35 | H35: =G35*(1-'Допущения'!$D$25/4)+H33*'Допущения'!$D$35 | I35: =H35*(1-'Допущения'!$D$25/4)+I33*'Допущения'!$D$35 | J35: =I35*(1-'Допущения'!$D$25/4)+J33*'Допущения'!$D$35 | K35: =J35*(1-'Допущения'!$D$25/4)+K33*'Допущения'!$D$35 | ... V35: =U35*(1-'Допущения'!$D$25/4)+V33*'Допущения'!$D$35 | X35: =F35 | Y35: =J35 | Z35: =N35 | AA35: =R35 | AB35: =V35 | AC35: =V35
A36: 2. Доход от сохранённых клиентов | B36: млн ₽ | C36: =C35*$C$14/4/1000000 | D36: =D35*$C$14/4/1000000 | E36: =E35*$C$14/4/1000000 | F36: =F35*$C$14/4/1000000 | G36: =G35*$C$14/4/1000000 | H36: =H35*$C$14/4/1000000 | I36: =I35*$C$14/4/1000000 | J36: =J35*$C$14/4/1000000 | ... V36: =V35*$C$14/4/1000000 | X36: =SUM(C36:F36) | Y36: =SUM(G36:J36) | Z36: =SUM(K36:N36) | AA36: =SUM(O36:R36) | AB36: =SUM(S36:V36) | AC36: =SUM(C36:V36)
A37: Дополнительно удержанные пользователи раздела, накопительно | B37: чел. | C37: =C31*1000*'Допущения'!$D$41/4 | D37: =C37*(1-'Допущения'!$D$25/4)+D31*1000*'Допущения'!$D$41/4 | E37: =D37*(1-'Допущения'!$D$25/4)+E31*1000*'Допущения'!$D$41/4 | F37: =E37*(1-'Допущения'!$D$25/4)+F31*1000*'Допущения'!$D$41/4 | G37: =F37*(1-'Допущения'!$D$25/4)+G31*1000*'Допущения'!$D$41/4 | H37: =G37*(1-'Допущения'!$D$25/4)+H31*1000*'Допущения'!$D$41/4 | I37: =H37*(1-'Допущения'!$D$25/4)+I31*1000*'Допущения'!$D$41/4 | J37: =I37*(1-'Допущения'!$D$25/4)+J31*1000*'Допущения'!$D$41/4 | K37: =J37*(1-'Допущения'!$D$25/4)+K31*1000*'Допущения'!$D$41/4 | ... V37: =U37*(1-'Допущения'!$D$25/4)+V31*1000*'Допущения'!$D$41/4 | X37: =F37 | Y37: =J37 | Z37: =N37 | AA37: =R37 | AB37: =V37 | AC37: =V37
A38: 3. Доход от снижения оттока | B38: млн ₽ | C38: =C37*$C$14/4/1000000 | D38: =D37*$C$14/4/1000000 | E38: =E37*$C$14/4/1000000 | F38: =F37*$C$14/4/1000000 | G38: =G37*$C$14/4/1000000 | H38: =H37*$C$14/4/1000000 | I38: =I37*$C$14/4/1000000 | J38: =J37*$C$14/4/1000000 | ... V38: =V37*$C$14/4/1000000 | X38: =SUM(C38:F38) | Y38: =SUM(G38:J38) | Z38: =SUM(K38:N38) | AA38: =SUM(O38:R38) | AB38: =SUM(S38:V38) | AC38: =SUM(C38:V38)
A39: Новые клиенты благодаря продукту, накопительно | B39: чел. | C39: ='Допущения'!$D$44/4*'Допущения'!$D$45*C26 | D39: =C39*(1-'Допущения'!$D$25/4)+'Допущения'!$D$44/4*'Допущения'!$D$45*D26 | E39: =D39*(1-'Допущения'!$D$25/4)+'Допущения'!$D$44/4*'Допущения'!$D$45*E26 | F39: =E39*(1-'Допущения'!$D$25/4)+'Допущения'!$D$44/4*'Допущения'!$D$45*F26 | G39: =F39*(1-'Допущения'!$D$25/4)+'Допущения'!$D$44/4*'Допущения'!$D$45*G26 | H39: =G39*(1-'Допущения'!$D$25/4)+'Допущения'!$D$44/4*'Допущения'!$D$45*H26 | I39: =H39*(1-'Допущения'!$D$25/4)+'Допущения'!$D$44/4*'Допущения'!$D$45*I26 | J39: =I39*(1-'Допущения'!$D$25/4)+'Допущения'!$D$44/4*'Допущения'!$D$45*J26 | K39: =J39*(1-'Допущения'!$D$25/4)+'Допущения'!$D$44/4*'Допущения'!$D$45*K26 | ... V39: =U39*(1-'Допущения'!$D$25/4)+'Допущения'!$D$44/4*'Допущения'!$D$45*V26 | X39: =F39 | Y39: =J39 | Z39: =N39 | AA39: =R39 | AB39: =V39 | AC39: =V39
A40: 4. Доход от новых клиентов | B40: млн ₽ | C40: =C39*$C$14/4/1000000 | D40: =D39*$C$14/4/1000000 | E40: =E39*$C$14/4/1000000 | F40: =F39*$C$14/4/1000000 | G40: =G39*$C$14/4/1000000 | H40: =H39*$C$14/4/1000000 | I40: =I39*$C$14/4/1000000 | J40: =J39*$C$14/4/1000000 | ... V40: =V39*$C$14/4/1000000 | X40: =SUM(C40:F40) | Y40: =SUM(G40:J40) | Z40: =SUM(K40:N40) | AA40: =SUM(O40:R40) | AB40: =SUM(S40:V40) | AC40: =SUM(C40:V40)
A41: Обращения в КЦ, закрытые самообслуживанием | B41: шт. | C41: =$C$9*1000*'Допущения'!$D$42/4*'Допущения'!$D$43*C27 | D41: =$C$9*1000*'Допущения'!$D$42/4*'Допущения'!$D$43*D27 | E41: =$C$9*1000*'Допущения'!$D$42/4*'Допущения'!$D$43*E27 | F41: =$C$9*1000*'Допущения'!$D$42/4*'Допущения'!$D$43*F27 | G41: =$C$9*1000*'Допущения'!$D$42/4*'Допущения'!$D$43*G27 | H41: =$C$9*1000*'Допущения'!$D$42/4*'Допущения'!$D$43*H27 | I41: =$C$9*1000*'Допущения'!$D$42/4*'Допущения'!$D$43*I27 | J41: =$C$9*1000*'Допущения'!$D$42/4*'Допущения'!$D$43*J27 | ... V41: =$C$9*1000*'Допущения'!$D$42/4*'Допущения'!$D$43*V27 | X41: =SUM(C41:F41) | Y41: =SUM(G41:J41) | Z41: =SUM(K41:N41) | AA41: =SUM(O41:R41) | AB41: =SUM(S41:V41) | AC41: =SUM(C41:V41)
A42: 5. Экономия контакт-центра | B42: млн ₽ | C42: =C41*'Допущения'!$D$31/1000000 | D42: =D41*'Допущения'!$D$31/1000000 | E42: =E41*'Допущения'!$D$31/1000000 | F42: =F41*'Допущения'!$D$31/1000000 | G42: =G41*'Допущения'!$D$31/1000000 | H42: =H41*'Допущения'!$D$31/1000000 | I42: =I41*'Допущения'!$D$31/1000000 | J42: =J41*'Допущения'!$D$31/1000000 | ... V42: =V41*'Допущения'!$D$31/1000000 | X42: =SUM(C42:F42) | Y42: =SUM(G42:J42) | Z42: =SUM(K42:N42) | AA42: =SUM(O42:R42) | AB42: =SUM(S42:V42) | AC42: =SUM(C42:V42)
A43: Эффект для банка — мост из «Детского банка» и «Пушкинская карта»
A44: Мост 14 лет: дополнительно оставшиеся подростки, накопительно | B44: чел. | C44: =$C$20/4*C26 | D44: =C44*(1-'Допущения'!$D$25/4)+$C$20/4*D26 | E44: =D44*(1-'Допущения'!$D$25/4)+$C$20/4*E26 | F44: =E44*(1-'Допущения'!$D$25/4)+$C$20/4*F26 | G44: =F44*(1-'Допущения'!$D$25/4)+$C$20/4*G26 | H44: =G44*(1-'Допущения'!$D$25/4)+$C$20/4*H26 | I44: =H44*(1-'Допущения'!$D$25/4)+$C$20/4*I26 | J44: =I44*(1-'Допущения'!$D$25/4)+$C$20/4*J26 | K44: =J44*(1-'Допущения'!$D$25/4)+$C$20/4*K26 | ... V44: =U44*(1-'Допущения'!$D$25/4)+$C$20/4*V26 | X44: =F44 | Y44: =J44 | Z44: =N44 | AA44: =R44 | AB44: =V44 | AC44: =V44
A45: 8. Доход от моста «Детский банк» → «Старт» | B45: млн ₽ | C45: =C44*$C$14/4/1000000 | D45: =D44*$C$14/4/1000000 | E45: =E44*$C$14/4/1000000 | F45: =F44*$C$14/4/1000000 | G45: =G44*$C$14/4/1000000 | H45: =H44*$C$14/4/1000000 | I45: =I44*$C$14/4/1000000 | J45: =J44*$C$14/4/1000000 | ... V45: =V44*$C$14/4/1000000 | X45: =SUM(C45:F45) | Y45: =SUM(G45:J45) | Z45: =SUM(K45:N45) | AA45: =SUM(O45:R45) | AB45: =SUM(S45:V45) | AC45: =SUM(C45:V45)
A46: Пушкинская карта: новые клиенты через «Старт», накопительно | B46: чел. | C46: =$C$21/4*C26 | D46: =C46*(1-'Допущения'!$D$25/4)+$C$21/4*D26 | E46: =D46*(1-'Допущения'!$D$25/4)+$C$21/4*E26 | F46: =E46*(1-'Допущения'!$D$25/4)+$C$21/4*F26 | G46: =F46*(1-'Допущения'!$D$25/4)+$C$21/4*G26 | H46: =G46*(1-'Допущения'!$D$25/4)+$C$21/4*H26 | I46: =H46*(1-'Допущения'!$D$25/4)+$C$21/4*I26 | J46: =I46*(1-'Допущения'!$D$25/4)+$C$21/4*J26 | K46: =J46*(1-'Допущения'!$D$25/4)+$C$21/4*K26 | ... V46: =U46*(1-'Допущения'!$D$25/4)+$C$21/4*V26 | X46: =F46 | Y46: =J46 | Z46: =N46 | AA46: =R46 | AB46: =V46 | AC46: =V46
A47: 9. Доход от клиентов из «Пушкинской карты» | B47: млн ₽ | C47: =C46*$C$14/4/1000000 | D47: =D46*$C$14/4/1000000 | E47: =E46*$C$14/4/1000000 | F47: =F46*$C$14/4/1000000 | G47: =G46*$C$14/4/1000000 | H47: =H46*$C$14/4/1000000 | I47: =I46*$C$14/4/1000000 | J47: =J46*$C$14/4/1000000 | ... V47: =V46*$C$14/4/1000000 | X47: =SUM(C47:F47) | Y47: =SUM(G47:J47) | Z47: =SUM(K47:N47) | AA47: =SUM(O47:R47) | AB47: =SUM(S47:V47) | AC47: =SUM(C47:V47)
A48: Эффект для банка — этап 2: перехват для клиентов 23+
A49: Предотвращённые дроп-кейсы 23+ | B49: шт. | C49: =$C$18/4*'Допущения'!$D$52*C28 | D49: =$C$18/4*'Допущения'!$D$52*D28 | E49: =$C$18/4*'Допущения'!$D$52*E28 | F49: =$C$18/4*'Допущения'!$D$52*F28 | G49: =$C$18/4*'Допущения'!$D$52*G28 | H49: =$C$18/4*'Допущения'!$D$52*H28 | I49: =$C$18/4*'Допущения'!$D$52*I28 | J49: =$C$18/4*'Допущения'!$D$52*J28 | ... V49: =$C$18/4*'Допущения'!$D$52*V28 | X49: =SUM(C49:F49) | Y49: =SUM(G49:J49) | Z49: =SUM(K49:N49) | AA49: =SUM(O49:R49) | AB49: =SUM(S49:V49) | AC49: =SUM(C49:V49)
A50: 6. Экономия на разборе дроп-кейсов 23+ | B50: млн ₽ | C50: =C49*$C$15/1000000 | D50: =D49*$C$15/1000000 | E50: =E49*$C$15/1000000 | F50: =F49*$C$15/1000000 | G50: =G49*$C$15/1000000 | H50: =H49*$C$15/1000000 | I50: =I49*$C$15/1000000 | J50: =J49*$C$15/1000000 | ... V50: =V49*$C$15/1000000 | X50: =SUM(C50:F50) | Y50: =SUM(G50:J50) | Z50: =SUM(K50:N50) | AA50: =SUM(O50:R50) | AB50: =SUM(S50:V50) | AC50: =SUM(C50:V50)
A51: Сохранённые взрослые клиенты, накопительно | B51: чел. | C51: =C49*'Допущения'!$D$35 | D51: =C51*(1-'Допущения'!$D$54/4)+D49*'Допущения'!$D$35 | E51: =D51*(1-'Допущения'!$D$54/4)+E49*'Допущения'!$D$35 | F51: =E51*(1-'Допущения'!$D$54/4)+F49*'Допущения'!$D$35 | G51: =F51*(1-'Допущения'!$D$54/4)+G49*'Допущения'!$D$35 | H51: =G51*(1-'Допущения'!$D$54/4)+H49*'Допущения'!$D$35 | I51: =H51*(1-'Допущения'!$D$54/4)+I49*'Допущения'!$D$35 | J51: =I51*(1-'Допущения'!$D$54/4)+J49*'Допущения'!$D$35 | K51: =J51*(1-'Допущения'!$D$54/4)+K49*'Допущения'!$D$35 | ... V51: =U51*(1-'Допущения'!$D$54/4)+V49*'Допущения'!$D$35 | X51: =F51 | Y51: =J51 | Z51: =N51 | AA51: =R51 | AB51: =V51 | AC51: =V51
A52: 7. Доход от сохранённых взрослых клиентов | B52: млн ₽ | C52: =C51*'Допущения'!$D$53/4/1000000 | D52: =D51*'Допущения'!$D$53/4/1000000 | E52: =E51*'Допущения'!$D$53/4/1000000 | F52: =F51*'Допущения'!$D$53/4/1000000 | G52: =G51*'Допущения'!$D$53/4/1000000 | H52: =H51*'Допущения'!$D$53/4/1000000 | I52: =I51*'Допущения'!$D$53/4/1000000 | J52: =J51*'Допущения'!$D$53/4/1000000 | ... V52: =V51*'Допущения'!$D$53/4/1000000 | X52: =SUM(C52:F52) | Y52: =SUM(G52:J52) | Z52: =SUM(K52:N52) | AA52: =SUM(O52:R52) | AB52: =SUM(S52:V52) | AC52: =SUM(C52:V52)
A53: ИТОГО ЭФФЕКТ | B53: млн ₽ | C53: =C34+C36+C38+C40+C42+C45+C47+C50+C52 | D53: =D34+D36+D38+D40+D42+D45+D47+D50+D52 | E53: =E34+E36+E38+E40+E42+E45+E47+E50+E52 | F53: =F34+F36+F38+F40+F42+F45+F47+F50+F52 | G53: =G34+G36+G38+G40+G42+G45+G47+G50+G52 | H53: =H34+H36+H38+H40+H42+H45+H47+H50+H52 | I53: =I34+I36+I38+I40+I42+I45+I47+I50+I52 | J53: =J34+J36+J38+J40+J42+J45+J47+J50+J52 | ... V53: =V34+V36+V38+V40+V42+V45+V47+V50+V52 | X53: =SUM(C53:F53) | Y53: =SUM(G53:J53) | Z53: =SUM(K53:N53) | AA53: =SUM(O53:R53) | AB53: =SUM(S53:V53) | AC53: =SUM(C53:V53)
A54: Затраты на внедрение и поддержку
A55: Команда: разработка и пилот | B55: млн ₽ | C55: =C25*SUMPRODUCT('Допущения'!$C$85:$C$93,'Допущения'!$B$85:$B$93)*1000*$C$17*3/1000000 | D55: =D25*SUMPRODUCT('Допущения'!$C$85:$C$93,'Допущения'!$B$85:$B$93)*1000*$C$17*3/1000000 | E55: =E25*SUMPRODUCT('Допущения'!$C$85:$C$93,'Допущения'!$B$85:$B$93)*1000*$C$17*3/1000000 | F55: =F25*SUMPRODUCT('Допущения'!$C$85:$C$93,'Допущения'!$B$85:$B$93)*1000*$C$17*3/1000000 | G55: =G25*SUMPRODUCT('Допущения'!$C$85:$C$93,'Допущения'!$B$85:$B$93)*1000*$C$17*3/1000000 | H55: =H25*SUMPRODUCT('Допущения'!$C$85:$C$93,'Допущения'!$B$85:$B$93)*1000*$C$17*3/1000000 | I55: =I25*SUMPRODUCT('Допущения'!$C$85:$C$93,'Допущения'!$B$85:$B$93)*1000*$C$17*3/1000000 | J55: =J25*SUMPRODUCT('Допущения'!$C$85:$C$93,'Допущения'!$B$85:$B$93)*1000*$C$17*3/1000000 | ... V55: =V25*SUMPRODUCT('Допущения'!$C$85:$C$93,'Допущения'!$B$85:$B$93)*1000*$C$17*3/1000000 | X55: =SUM(C55:F55) | Y55: =SUM(G55:J55) | Z55: =SUM(K55:N55) | AA55: =SUM(O55:R55) | AB55: =SUM(S55:V55) | AC55: =SUM(C55:V55)
A56: Команда: эксплуатация и развитие | B56: млн ₽ | C56: =(1-C25)*SUMPRODUCT('Допущения'!$D$85:$D$93,'Допущения'!$B$85:$B$93)*1000*$C$17*3/1000000 | D56: =(1-D25)*SUMPRODUCT('Допущения'!$D$85:$D$93,'Допущения'!$B$85:$B$93)*1000*$C$17*3/1000000 | E56: =(1-E25)*SUMPRODUCT('Допущения'!$D$85:$D$93,'Допущения'!$B$85:$B$93)*1000*$C$17*3/1000000 | F56: =(1-F25)*SUMPRODUCT('Допущения'!$D$85:$D$93,'Допущения'!$B$85:$B$93)*1000*$C$17*3/1000000 | G56: =(1-G25)*SUMPRODUCT('Допущения'!$D$85:$D$93,'Допущения'!$B$85:$B$93)*1000*$C$17*3/1000000 | H56: =(1-H25)*SUMPRODUCT('Допущения'!$D$85:$D$93,'Допущения'!$B$85:$B$93)*1000*$C$17*3/1000000 | I56: =(1-I25)*SUMPRODUCT('Допущения'!$D$85:$D$93,'Допущения'!$B$85:$B$93)*1000*$C$17*3/1000000 | J56: =(1-J25)*SUMPRODUCT('Допущения'!$D$85:$D$93,'Допущения'!$B$85:$B$93)*1000*$C$17*3/1000000 | ... V56: =(1-V25)*SUMPRODUCT('Допущения'!$D$85:$D$93,'Допущения'!$B$85:$B$93)*1000*$C$17*3/1000000 | X56: =SUM(C56:F56) | Y56: =SUM(G56:J56) | Z56: =SUM(K56:N56) | AA56: =SUM(O56:R56) | AB56: =SUM(S56:V56) | AC56: =SUM(C56:V56)
A57: Инфраструктура, ИБ, контент, маркетинг (график) | B57: млн ₽ | C57: =SUM('Допущения'!C$101:C$106) | D57: =SUM('Допущения'!D$101:D$106) | E57: =SUM('Допущения'!E$101:E$106) | F57: =SUM('Допущения'!F$101:F$106) | G57: =SUM('Допущения'!G$101:G$106) | H57: =SUM('Допущения'!H$101:H$106) | I57: =SUM('Допущения'!I$101:I$106) | J57: =SUM('Допущения'!J$101:J$106) | ... V57: =SUM('Допущения'!V$101:V$106) | X57: =SUM(C57:F57) | Y57: =SUM(G57:J57) | Z57: =SUM(K57:N57) | AA57: =SUM(O57:R57) | AB57: =SUM(S57:V57) | AC57: =SUM(C57:V57)
A58: Мост и «Пушкинская карта»: интеграция и поддержка | B58: млн ₽ | C58: ='Допущения'!C$108*'Допущения'!$D$62+'Допущения'!C$109*'Допущения'!$D$66 | D58: ='Допущения'!D$108*'Допущения'!$D$62+'Допущения'!D$109*'Допущения'!$D$66 | E58: ='Допущения'!E$108*'Допущения'!$D$62+'Допущения'!E$109*'Допущения'!$D$66 | F58: ='Допущения'!F$108*'Допущения'!$D$62+'Допущения'!F$109*'Допущения'!$D$66 | G58: ='Допущения'!G$108*'Допущения'!$D$62+'Допущения'!G$109*'Допущения'!$D$66 | H58: ='Допущения'!H$108*'Допущения'!$D$62+'Допущения'!H$109*'Допущения'!$D$66 | I58: ='Допущения'!I$108*'Допущения'!$D$62+'Допущения'!I$109*'Допущения'!$D$66 | J58: ='Допущения'!J$108*'Допущения'!$D$62+'Допущения'!J$109*'Допущения'!$D$66 | ... V58: ='Допущения'!V$108*'Допущения'!$D$62+'Допущения'!V$109*'Допущения'!$D$66 | X58: =SUM(C58:F58) | Y58: =SUM(G58:J58) | Z58: =SUM(K58:N58) | AA58: =SUM(O58:R58) | AB58: =SUM(S58:V58) | AC58: =SUM(C58:V58)
A59: Этап 2: доработка и поддержка для клиентов 23+ | B59: млн ₽ | C59: ='Допущения'!C$107*'Допущения'!$D$48 | D59: ='Допущения'!D$107*'Допущения'!$D$48 | E59: ='Допущения'!E$107*'Допущения'!$D$48 | F59: ='Допущения'!F$107*'Допущения'!$D$48 | G59: ='Допущения'!G$107*'Допущения'!$D$48 | H59: ='Допущения'!H$107*'Допущения'!$D$48 | I59: ='Допущения'!I$107*'Допущения'!$D$48 | J59: ='Допущения'!J$107*'Допущения'!$D$48 | ... V59: ='Допущения'!V$107*'Допущения'!$D$48 | X59: =SUM(C59:F59) | Y59: =SUM(G59:J59) | Z59: =SUM(K59:N59) | AA59: =SUM(O59:R59) | AB59: =SUM(S59:V59) | AC59: =SUM(C59:V59)
A60: Вознаграждения пользователям | B60: млн ₽ | C60: =C31*1000*'Допущения'!$D$78/4/1000000 | D60: =D31*1000*'Допущения'!$D$78/4/1000000 | E60: =E31*1000*'Допущения'!$D$78/4/1000000 | F60: =F31*1000*'Допущения'!$D$78/4/1000000 | G60: =G31*1000*'Допущения'!$D$78/4/1000000 | H60: =H31*1000*'Допущения'!$D$78/4/1000000 | I60: =I31*1000*'Допущения'!$D$78/4/1000000 | J60: =J31*1000*'Допущения'!$D$78/4/1000000 | ... V60: =V31*1000*'Допущения'!$D$78/4/1000000 | X60: =SUM(C60:F60) | Y60: =SUM(G60:J60) | Z60: =SUM(K60:N60) | AA60: =SUM(O60:R60) | AB60: =SUM(S60:V60) | AC60: =SUM(C60:V60)
A61: Резерв на непредвиденное | B61: млн ₽ | C61: =(C55+C56+C57+C58+C59+C60)*'Допущения'!$D$79 | D61: =(D55+D56+D57+D58+D59+D60)*'Допущения'!$D$79 | E61: =(E55+E56+E57+E58+E59+E60)*'Допущения'!$D$79 | F61: =(F55+F56+F57+F58+F59+F60)*'Допущения'!$D$79 | G61: =(G55+G56+G57+G58+G59+G60)*'Допущения'!$D$79 | H61: =(H55+H56+H57+H58+H59+H60)*'Допущения'!$D$79 | I61: =(I55+I56+I57+I58+I59+I60)*'Допущения'!$D$79 | J61: =(J55+J56+J57+J58+J59+J60)*'Допущения'!$D$79 | ... V61: =(V55+V56+V57+V58+V59+V60)*'Допущения'!$D$79 | X61: =SUM(C61:F61) | Y61: =SUM(G61:J61) | Z61: =SUM(K61:N61) | AA61: =SUM(O61:R61) | AB61: =SUM(S61:V61) | AC61: =SUM(C61:V61)
A62: ИТОГО ЗАТРАТЫ (с учётом перерасхода) | B62: млн ₽ | C62: =(C55+C56+C57+C58+C59+C60+C61)*'Допущения'!$D$80 | D62: =(D55+D56+D57+D58+D59+D60+D61)*'Допущения'!$D$80 | E62: =(E55+E56+E57+E58+E59+E60+E61)*'Допущения'!$D$80 | F62: =(F55+F56+F57+F58+F59+F60+F61)*'Допущения'!$D$80 | G62: =(G55+G56+G57+G58+G59+G60+G61)*'Допущения'!$D$80 | H62: =(H55+H56+H57+H58+H59+H60+H61)*'Допущения'!$D$80 | I62: =(I55+I56+I57+I58+I59+I60+I61)*'Допущения'!$D$80 | J62: =(J55+J56+J57+J58+J59+J60+J61)*'Допущения'!$D$80 | ... V62: =(V55+V56+V57+V58+V59+V60+V61)*'Допущения'!$D$80 | X62: =SUM(C62:F62) | Y62: =SUM(G62:J62) | Z62: =SUM(K62:N62) | AA62: =SUM(O62:R62) | AB62: =SUM(S62:V62) | AC62: =SUM(C62:V62)
A63: Денежный поток
A64: Чистый денежный поток | B64: млн ₽ | C64: =C53-C62 | D64: =D53-D62 | E64: =E53-E62 | F64: =F53-F62 | G64: =G53-G62 | H64: =H53-H62 | I64: =I53-I62 | J64: =J53-J62 | ... V64: =V53-V62 | X64: =SUM(C64:F64) | Y64: =SUM(G64:J64) | Z64: =SUM(K64:N64) | AA64: =SUM(O64:R64) | AB64: =SUM(S64:V64) | AC64: =SUM(C64:V64)
A65: Накопленный денежный поток | B65: млн ₽ | C65: =C64 | D65: =C65+D64 | E65: =D65+E64 | F65: =E65+F64 | G65: =F65+G64 | H65: =G65+H64 | I65: =H65+I64 | J65: =I65+J64 | K65: =J65+K64 | ... V65: =U65+V64 | X65: =F65 | Y65: =J65 | Z65: =N65 | AA65: =R65 | AB65: =V65 | AC65: =V65
A66: Коэффициент дисконтирования | B66: x | C66: =1/(1+$C$16)^C24 | D66: =1/(1+$C$16)^D24 | E66: =1/(1+$C$16)^E24 | F66: =1/(1+$C$16)^F24 | G66: =1/(1+$C$16)^G24 | H66: =1/(1+$C$16)^H24 | I66: =1/(1+$C$16)^I24 | J66: =1/(1+$C$16)^J24 | ... V66: =1/(1+$C$16)^V24
A67: Дисконтированный поток | B67: млн ₽ | C67: =C64*C66 | D67: =D64*D66 | E67: =E64*E66 | F67: =F64*F66 | G67: =G64*G66 | H67: =H64*H66 | I67: =I64*I66 | J67: =J64*J66 | ... V67: =V64*V66 | X67: =SUM(C67:F67) | Y67: =SUM(G67:J67) | Z67: =SUM(K67:N67) | AA67: =SUM(O67:R67) | AB67: =SUM(S67:V67) | AC67: =SUM(C67:V67)
A68: Служебная: номер квартала, если накопленный поток ≥ 0 | B68: № | C68: =IF(C65>=0,C24,99) | D68: =IF(D65>=0,D24,99) | E68: =IF(E65>=0,E24,99) | F68: =IF(F65>=0,F24,99) | G68: =IF(G65>=0,G24,99) | H68: =IF(H65>=0,H24,99) | I68: =IF(I65>=0,I24,99) | J68: =IF(J65>=0,J24,99) | ... V68: =IF(V65>=0,V24,99)
A69: Поток ядра продукта: без этапа 2, моста и «Пушкинской карты» | B69: млн ₽ | C69: =(C53-C50-C52-C45-C47)-(C55+C56+C57+C60)*(1+'Допущения'!$D$79)*'Допущения'!$D$80 | D69: =(D53-D50-D52-D45-D47)-(D55+D56+D57+D60)*(1+'Допущения'!$D$79)*'Допущения'!$D$80 | E69: =(E53-E50-E52-E45-E47)-(E55+E56+E57+E60)*(1+'Допущения'!$D$79)*'Допущения'!$D$80 | F69: =(F53-F50-F52-F45-F47)-(F55+F56+F57+F60)*(1+'Допущения'!$D$79)*'Допущения'!$D$80 | G69: =(G53-G50-G52-G45-G47)-(G55+G56+G57+G60)*(1+'Допущения'!$D$79)*'Допущения'!$D$80 | H69: =(H53-H50-H52-H45-H47)-(H55+H56+H57+H60)*(1+'Допущения'!$D$79)*'Допущения'!$D$80 | I69: =(I53-I50-I52-I45-I47)-(I55+I56+I57+I60)*(1+'Допущения'!$D$79)*'Допущения'!$D$80 | J69: =(J53-J50-J52-J45-J47)-(J55+J56+J57+J60)*(1+'Допущения'!$D$79)*'Допущения'!$D$80 | ... V69: =(V53-V50-V52-V45-V47)-(V55+V56+V57+V60)*(1+'Допущения'!$D$79)*'Допущения'!$D$80 | X69: =SUM(C69:F69) | Y69: =SUM(G69:J69) | Z69: =SUM(K69:N69) | AA69: =SUM(O69:R69) | AB69: =SUM(S69:V69) | AC69: =SUM(C69:V69)
A70: Итоговые показатели сценария
A71: NPV за 5 лет (2027–2031) | B71: млн ₽ | C71: =SUM(C67:V67)
A72: NPV за 5 лет только ядра продукта (без этапа 2, моста и «Пушкинской карты») | B72: млн ₽ | C72: =SUMPRODUCT(C69:V69,C66:V66)
A73: NPV за первые 3 года (2027–2029), справочно | B73: млн ₽ | C73: =SUM(C67:N67)
A74: Суммарный эффект за 5 лет | B74: млн ₽ | C74: =AC53
A75: Суммарные затраты за 5 лет | B75: млн ₽ | C75: =AC62
A76: ROI за 5 лет | B76: доля | C76: =IF(C75>0,(C74-C75)/C75,0)
A77: Инвестиции до полного запуска (разработка + пилот) | B77: млн ₽ | C77: =SUMPRODUCT(C62:V62,C25:V25)
A78: Квартал окупаемости (99 — не окупается за 5 лет) | B78: № | C78: =MIN(C68:V68)
A79: Срок окупаемости от старта проекта | B79: мес. | C79: =IF(C78=99,"больше 60",IF(C78=1,0,(C78-1)*3+3*(-INDEX(C65:V65,C78-1))/INDEX(C64:V64,C78)))
A80: Срок окупаемости от полного запуска | B80: мес. | C80: =IF(C78=99,"больше 60",C79-('Допущения'!$D$75-1)*3)
A81: Годовые затраты в режиме эксплуатации (2031) | B81: млн ₽ | C81: =AB62
A82: Годовой эффект (2031) | B82: млн ₽ | C82: =AB53
A83: Операционный поток 2029 (эффект минус затраты) | B83: млн ₽ | C83: =Z53-Z62
A84: Предотвращено дроп-кейсов молодёжи за 5 лет | B84: шт. | C84: =AC33
A85: Предотвращено дроп-кейсов 23+ за 5 лет | B85: шт. | C85: =AC49
A86: Социальный эффект: чужих денег не прошло через карты ВТБ (вне NPV) | B86: млн ₽ | C86: =(C84+C85)*'Допущения'!$D$36/1000000
A87: MAU раздела на конец 2031 | B87: тыс. чел. | C87: =V31
A88: Молодых клиентов сохранено, удержано и привлечено (на конец 2031) | B88: чел. | C88: =V35+V37+V39+V44+V46
A89: Стратегическая ценность этих клиентов после 23 лет (вне NPV) | B89: млн ₽ | C89: =C88*C19/1000000
A90: Затраты на одного MAU в 2031 | B90: ₽/год | C90: =IF(V31>0,AB62*1000000/(V31*1000),0)

Sheet Расчёт_О
A1: Расчёт: Оптимистичный сценарий
A2: Все значения — формулы от листа «Допущения» (колонка сценария). Деньги — млн ₽.
A4: Аудитория и базовые величины
A5: Молодёжь 14–17 лет в РФ | B5: тыс. чел. | C5: ='Допущения'!$E$8*'Допущения'!$E$9
A6: Молодёжь 18–22 лет в РФ | B6: тыс. чел. | C6: ='Допущения'!$E$7*'Допущения'!$E$9
A7: TAM: вся молодёжь 14–22 | B7: тыс. чел. | C7: =C5+C6
A8: SAM: молодёжь 14–22 с банковской картой | B8: тыс. чел. | C8: =C5*'Допущения'!$E$10+C6*'Допущения'!$E$11
A9: SOM: клиенты ВТБ 14–22 | B9: тыс. чел. | C9: =C5*'Допущения'!$E$10*'Допущения'!$E$12+C6*'Допущения'!$E$11*'Допущения'!$E$13
A10: Проверка: клиенты ВТБ 14–25 по модели (факт ВТБ — на листе «Допущения») | B10: тыс. чел. | C10: =C9+'Допущения'!$E$16*'Допущения'!$E$9*'Допущения'!$E$11*'Допущения'!$E$13
A11: Дропов 14–22 лет в РФ в год | B11: тыс. чел. | C11: ='Допущения'!$E$14*12*'Допущения'!$E$15/1000
A12: Вероятность стать дропом за год для молодого клиента с картой | B12: доля | C12: =IF(C8>0,C11/C8,0)
A13: Дроп-кейсов среди клиентов ВТБ 14–22 в год (без продукта) | B13: шт. | C13: =C9*1000*C12
A14: Маржинальный доход на молодого клиента | B14: ₽/год | C14: ='Допущения'!$E$20*12*'Допущения'!$E$21+'Допущения'!$E$22*'Допущения'!$E$23-'Допущения'!$E$24
A15: Затраты банка на один дроп-кейс | B15: ₽ | C15: ='Допущения'!$E$28*'Допущения'!$E$29+'Допущения'!$E$30*'Допущения'!$E$31+'Допущения'!$E$32*'Допущения'!$E$33+'Допущения'!$E$34
A16: Квартальная ставка дисконтирования | B16: доля | C16: =(1+'Допущения'!$E$81)^(1/4)-1
A17: Полная стоимость сотрудника к зарплате (взносы + накладные) | B17: x | C17: =(1+'Допущения'!$E$76)*(1+'Допущения'!$E$77)
A18: Этап 2: дроп-кейсов среди клиентов ВТБ 23+ в год (без продукта) | B18: шт. | C18: ='Допущения'!$E$14*12*'Допущения'!$E$50*'Допущения'!$E$51
A19: Ценность будущего взрослого клиента на сегодня (на одного молодого клиента) | B19: ₽ | C19: ='Допущения'!$E$57*'Допущения'!$E$53*(1-(1+'Допущения'!$E$81)^(-'Допущения'!$E$59))/'Допущения'!$E$81/(1+'Допущения'!$E$81)^'Допущения'!$E$58
A20: Мост: дополнительно остаются в ВТБ при переходе в 14 лет | B20: чел./год | C20: ='Допущения'!$E$63*'Допущения'!$E$64*'Допущения'!$E$65*'Допущения'!$E$62
A21: Пушкинская карта: новых клиентов через «Старт» | B21: чел./год | C21: ='Допущения'!$E$67*'Допущения'!$E$68*'Допущения'!$E$69*'Допущения'!$E$66
A23: Показатель | B23: Ед. | C23: Q1 2027 | D23: Q2 2027 | E23: Q3 2027 | F23: Q4 2027 | G23: Q1 2028 | H23: Q2 2028 | I23: Q3 2028 | J23: Q4 2028 | K23: Q1 2029 | L23: Q2 2029 | M23: Q3 2029 | N23: Q4 2029 | O23: Q1 2030 | P23: Q2 2030 | Q23: Q3 2030 | R23: Q4 2030 | S23: Q1 2031 | T23: Q2 2031 | U23: Q3 2031 | V23: Q4 2031 | X23: 2027 | Y23: 2028 | Z23: 2029 | AA23: 2030 | AB23: 2031 | AC23: Итого
A24: Номер квартала | B24: № | C24: =1 | D24: =C24+1 | E24: =D24+1 | F24: =E24+1 | G24: =F24+1 | H24: =G24+1 | I24: =H24+1 | J24: =I24+1 | K24: =J24+1 | ... V24: =U24+1
A25: Флаг: разработка и пилот (полная команда) | B25: 0/1 | C25: =IF(C24<='Допущения'!$E$74,1,0) | D25: =IF(D24<='Допущения'!$E$74,1,0) | E25: =IF(E24<='Допущения'!$E$74,1,0) | F25: =IF(F24<='Допущения'!$E$74,1,0) | G25: =IF(G24<='Допущения'!$E$74,1,0) | H25: =IF(H24<='Допущения'!$E$74,1,0) | I25: =IF(I24<='Допущения'!$E$74,1,0) | J25: =IF(J24<='Допущения'!$E$74,1,0) | ... V25: =IF(V24<='Допущения'!$E$74,1,0)
A26: Флаг: продукт запущен для всех | B26: 0/1 | C26: =IF(C24>='Допущения'!$E$75,1,0) | D26: =IF(D24>='Допущения'!$E$75,1,0) | E26: =IF(E24>='Допущения'!$E$75,1,0) | F26: =IF(F24>='Допущения'!$E$75,1,0) | G26: =IF(G24>='Допущения'!$E$75,1,0) | H26: =IF(H24>='Допущения'!$E$75,1,0) | I26: =IF(I24>='Допущения'!$E$75,1,0) | J26: =IF(J24>='Допущения'!$E$75,1,0) | ... V26: =IF(V24>='Допущения'!$E$75,1,0)
A27: Покрытие перехватом (доля молодых клиентов) | B27: доля | C27: ='Допущения'!C$100 | D27: ='Допущения'!D$100 | E27: ='Допущения'!E$100 | F27: ='Допущения'!F$100 | G27: ='Допущения'!G$100 | H27: ='Допущения'!H$100 | I27: ='Допущения'!I$100 | J27: ='Допущения'!J$100 | ... V27: ='Допущения'!V$100 | X27: =F27 | Y27: =J27 | Z27: =N27 | AA27: =R27 | AB27: =V27 | AC27: =V27
A28: Флаг: этап 2 (перехват для клиентов 23+) | B28: 0/1 | C28: =IF(C24>='Допущения'!$E$49,1,0)*'Допущения'!$E$48 | D28: =IF(D24>='Допущения'!$E$49,1,0)*'Допущения'!$E$48 | E28: =IF(E24>='Допущения'!$E$49,1,0)*'Допущения'!$E$48 | F28: =IF(F24>='Допущения'!$E$49,1,0)*'Допущения'!$E$48 | G28: =IF(G24>='Допущения'!$E$49,1,0)*'Допущения'!$E$48 | H28: =IF(H24>='Допущения'!$E$49,1,0)*'Допущения'!$E$48 | I28: =IF(I24>='Допущения'!$E$49,1,0)*'Допущения'!$E$48 | J28: =IF(J24>='Допущения'!$E$49,1,0)*'Допущения'!$E$48 | ... V28: =IF(V24>='Допущения'!$E$49,1,0)*'Допущения'!$E$48
A29: Охват раздела «Старт»
A30: Доля молодых клиентов ВТБ — MAU раздела | B30: доля | C30: =MIN('Допущения'!$E$73,'Допущения'!C$99*'Допущения'!$E$72) | D30: =MIN('Допущения'!$E$73,'Допущения'!D$99*'Допущения'!$E$72) | E30: =MIN('Допущения'!$E$73,'Допущения'!E$99*'Допущения'!$E$72) | F30: =MIN('Допущения'!$E$73,'Допущения'!F$99*'Допущения'!$E$72) | G30: =MIN('Допущения'!$E$73,'Допущения'!G$99*'Допущения'!$E$72) | H30: =MIN('Допущения'!$E$73,'Допущения'!H$99*'Допущения'!$E$72) | I30: =MIN('Допущения'!$E$73,'Допущения'!I$99*'Допущения'!$E$72) | J30: =MIN('Допущения'!$E$73,'Допущения'!J$99*'Допущения'!$E$72) | ... V30: =MIN('Допущения'!$E$73,'Допущения'!V$99*'Допущения'!$E$72) | X30: =F30 | Y30: =J30 | Z30: =N30 | AA30: =R30 | AB30: =V30 | AC30: =V30
A31: MAU раздела «Старт» | B31: тыс. чел. | C31: =$C$9*C30 | D31: =$C$9*D30 | E31: =$C$9*E30 | F31: =$C$9*F30 | G31: =$C$9*G30 | H31: =$C$9*H30 | I31: =$C$9*I30 | J31: =$C$9*J30 | ... V31: =$C$9*V30 | X31: =F31 | Y31: =J31 | Z31: =N31 | AA31: =R31 | AB31: =V31 | AC31: =V31
A32: Эффект для банка — молодёжь 14–22
A33: Предотвращённые дроп-кейсы (перехват у всех + уроки у MAU) | B33: шт. | C33: =$C$9*1000*$C$12/4*(C27*'Допущения'!$E$39+C30*'Допущения'!$E$40) | D33: =$C$9*1000*$C$12/4*(D27*'Допущения'!$E$39+D30*'Допущения'!$E$40) | E33: =$C$9*1000*$C$12/4*(E27*'Допущения'!$E$39+E30*'Допущения'!$E$40) | F33: =$C$9*1000*$C$12/4*(F27*'Допущения'!$E$39+F30*'Допущения'!$E$40) | G33: =$C$9*1000*$C$12/4*(G27*'Допущения'!$E$39+G30*'Допущения'!$E$40) | H33: =$C$9*1000*$C$12/4*(H27*'Допущения'!$E$39+H30*'Допущения'!$E$40) | I33: =$C$9*1000*$C$12/4*(I27*'Допущения'!$E$39+I30*'Допущения'!$E$40) | J33: =$C$9*1000*$C$12/4*(J27*'Допущения'!$E$39+J30*'Допущения'!$E$40) | ... V33: =$C$9*1000*$C$12/4*(V27*'Допущения'!$E$39+V30*'Допущения'!$E$40) | X33: =SUM(C33:F33) | Y33: =SUM(G33:J33) | Z33: =SUM(K33:N33) | AA33: =SUM(O33:R33) | AB33: =SUM(S33:V33) | AC33: =SUM(C33:V33)
A34: 1. Экономия на разборе дроп-кейсов | B34: млн ₽ | C34: =C33*$C$15/1000000 | D34: =D33*$C$15/1000000 | E34: =E33*$C$15/1000000 | F34: =F33*$C$15/1000000 | G34: =G33*$C$15/1000000 | H34: =H33*$C$15/1000000 | I34: =I33*$C$15/1000000 | J34: =J33*$C$15/1000000 | ... V34: =V33*$C$15/1000000 | X34: =SUM(C34:F34) | Y34: =SUM(G34:J34) | Z34: =SUM(K34:N34) | AA34: =SUM(O34:R34) | AB34: =SUM(S34:V34) | AC34: =SUM(C34:V34)
A35: Сохранённые клиенты (не потеряны из-за дропа), накопительно | B35: чел. | C35: =C33*'Допущения'!$E$35 | D35: =C35*(1-'Допущения'!$E$25/4)+D33*'Допущения'!$E$35 | E35: =D35*(1-'Допущения'!$E$25/4)+E33*'Допущения'!$E$35 | F35: =E35*(1-'Допущения'!$E$25/4)+F33*'Допущения'!$E$35 | G35: =F35*(1-'Допущения'!$E$25/4)+G33*'Допущения'!$E$35 | H35: =G35*(1-'Допущения'!$E$25/4)+H33*'Допущения'!$E$35 | I35: =H35*(1-'Допущения'!$E$25/4)+I33*'Допущения'!$E$35 | J35: =I35*(1-'Допущения'!$E$25/4)+J33*'Допущения'!$E$35 | K35: =J35*(1-'Допущения'!$E$25/4)+K33*'Допущения'!$E$35 | ... V35: =U35*(1-'Допущения'!$E$25/4)+V33*'Допущения'!$E$35 | X35: =F35 | Y35: =J35 | Z35: =N35 | AA35: =R35 | AB35: =V35 | AC35: =V35
A36: 2. Доход от сохранённых клиентов | B36: млн ₽ | C36: =C35*$C$14/4/1000000 | D36: =D35*$C$14/4/1000000 | E36: =E35*$C$14/4/1000000 | F36: =F35*$C$14/4/1000000 | G36: =G35*$C$14/4/1000000 | H36: =H35*$C$14/4/1000000 | I36: =I35*$C$14/4/1000000 | J36: =J35*$C$14/4/1000000 | ... V36: =V35*$C$14/4/1000000 | X36: =SUM(C36:F36) | Y36: =SUM(G36:J36) | Z36: =SUM(K36:N36) | AA36: =SUM(O36:R36) | AB36: =SUM(S36:V36) | AC36: =SUM(C36:V36)
A37: Дополнительно удержанные пользователи раздела, накопительно | B37: чел. | C37: =C31*1000*'Допущения'!$E$41/4 | D37: =C37*(1-'Допущения'!$E$25/4)+D31*1000*'Допущения'!$E$41/4 | E37: =D37*(1-'Допущения'!$E$25/4)+E31*1000*'Допущения'!$E$41/4 | F37: =E37*(1-'Допущения'!$E$25/4)+F31*1000*'Допущения'!$E$41/4 | G37: =F37*(1-'Допущения'!$E$25/4)+G31*1000*'Допущения'!$E$41/4 | H37: =G37*(1-'Допущения'!$E$25/4)+H31*1000*'Допущения'!$E$41/4 | I37: =H37*(1-'Допущения'!$E$25/4)+I31*1000*'Допущения'!$E$41/4 | J37: =I37*(1-'Допущения'!$E$25/4)+J31*1000*'Допущения'!$E$41/4 | K37: =J37*(1-'Допущения'!$E$25/4)+K31*1000*'Допущения'!$E$41/4 | ... V37: =U37*(1-'Допущения'!$E$25/4)+V31*1000*'Допущения'!$E$41/4 | X37: =F37 | Y37: =J37 | Z37: =N37 | AA37: =R37 | AB37: =V37 | AC37: =V37
A38: 3. Доход от снижения оттока | B38: млн ₽ | C38: =C37*$C$14/4/1000000 | D38: =D37*$C$14/4/1000000 | E38: =E37*$C$14/4/1000000 | F38: =F37*$C$14/4/1000000 | G38: =G37*$C$14/4/1000000 | H38: =H37*$C$14/4/1000000 | I38: =I37*$C$14/4/1000000 | J38: =J37*$C$14/4/1000000 | ... V38: =V37*$C$14/4/1000000 | X38: =SUM(C38:F38) | Y38: =SUM(G38:J38) | Z38: =SUM(K38:N38) | AA38: =SUM(O38:R38) | AB38: =SUM(S38:V38) | AC38: =SUM(C38:V38)
A39: Новые клиенты благодаря продукту, накопительно | B39: чел. | C39: ='Допущения'!$E$44/4*'Допущения'!$E$45*C26 | D39: =C39*(1-'Допущения'!$E$25/4)+'Допущения'!$E$44/4*'Допущения'!$E$45*D26 | E39: =D39*(1-'Допущения'!$E$25/4)+'Допущения'!$E$44/4*'Допущения'!$E$45*E26 | F39: =E39*(1-'Допущения'!$E$25/4)+'Допущения'!$E$44/4*'Допущения'!$E$45*F26 | G39: =F39*(1-'Допущения'!$E$25/4)+'Допущения'!$E$44/4*'Допущения'!$E$45*G26 | H39: =G39*(1-'Допущения'!$E$25/4)+'Допущения'!$E$44/4*'Допущения'!$E$45*H26 | I39: =H39*(1-'Допущения'!$E$25/4)+'Допущения'!$E$44/4*'Допущения'!$E$45*I26 | J39: =I39*(1-'Допущения'!$E$25/4)+'Допущения'!$E$44/4*'Допущения'!$E$45*J26 | K39: =J39*(1-'Допущения'!$E$25/4)+'Допущения'!$E$44/4*'Допущения'!$E$45*K26 | ... V39: =U39*(1-'Допущения'!$E$25/4)+'Допущения'!$E$44/4*'Допущения'!$E$45*V26 | X39: =F39 | Y39: =J39 | Z39: =N39 | AA39: =R39 | AB39: =V39 | AC39: =V39
A40: 4. Доход от новых клиентов | B40: млн ₽ | C40: =C39*$C$14/4/1000000 | D40: =D39*$C$14/4/1000000 | E40: =E39*$C$14/4/1000000 | F40: =F39*$C$14/4/1000000 | G40: =G39*$C$14/4/1000000 | H40: =H39*$C$14/4/1000000 | I40: =I39*$C$14/4/1000000 | J40: =J39*$C$14/4/1000000 | ... V40: =V39*$C$14/4/1000000 | X40: =SUM(C40:F40) | Y40: =SUM(G40:J40) | Z40: =SUM(K40:N40) | AA40: =SUM(O40:R40) | AB40: =SUM(S40:V40) | AC40: =SUM(C40:V40)
A41: Обращения в КЦ, закрытые самообслуживанием | B41: шт. | C41: =$C$9*1000*'Допущения'!$E$42/4*'Допущения'!$E$43*C27 | D41: =$C$9*1000*'Допущения'!$E$42/4*'Допущения'!$E$43*D27 | E41: =$C$9*1000*'Допущения'!$E$42/4*'Допущения'!$E$43*E27 | F41: =$C$9*1000*'Допущения'!$E$42/4*'Допущения'!$E$43*F27 | G41: =$C$9*1000*'Допущения'!$E$42/4*'Допущения'!$E$43*G27 | H41: =$C$9*1000*'Допущения'!$E$42/4*'Допущения'!$E$43*H27 | I41: =$C$9*1000*'Допущения'!$E$42/4*'Допущения'!$E$43*I27 | J41: =$C$9*1000*'Допущения'!$E$42/4*'Допущения'!$E$43*J27 | ... V41: =$C$9*1000*'Допущения'!$E$42/4*'Допущения'!$E$43*V27 | X41: =SUM(C41:F41) | Y41: =SUM(G41:J41) | Z41: =SUM(K41:N41) | AA41: =SUM(O41:R41) | AB41: =SUM(S41:V41) | AC41: =SUM(C41:V41)
A42: 5. Экономия контакт-центра | B42: млн ₽ | C42: =C41*'Допущения'!$E$31/1000000 | D42: =D41*'Допущения'!$E$31/1000000 | E42: =E41*'Допущения'!$E$31/1000000 | F42: =F41*'Допущения'!$E$31/1000000 | G42: =G41*'Допущения'!$E$31/1000000 | H42: =H41*'Допущения'!$E$31/1000000 | I42: =I41*'Допущения'!$E$31/1000000 | J42: =J41*'Допущения'!$E$31/1000000 | ... V42: =V41*'Допущения'!$E$31/1000000 | X42: =SUM(C42:F42) | Y42: =SUM(G42:J42) | Z42: =SUM(K42:N42) | AA42: =SUM(O42:R42) | AB42: =SUM(S42:V42) | AC42: =SUM(C42:V42)
A43: Эффект для банка — мост из «Детского банка» и «Пушкинская карта»
A44: Мост 14 лет: дополнительно оставшиеся подростки, накопительно | B44: чел. | C44: =$C$20/4*C26 | D44: =C44*(1-'Допущения'!$E$25/4)+$C$20/4*D26 | E44: =D44*(1-'Допущения'!$E$25/4)+$C$20/4*E26 | F44: =E44*(1-'Допущения'!$E$25/4)+$C$20/4*F26 | G44: =F44*(1-'Допущения'!$E$25/4)+$C$20/4*G26 | H44: =G44*(1-'Допущения'!$E$25/4)+$C$20/4*H26 | I44: =H44*(1-'Допущения'!$E$25/4)+$C$20/4*I26 | J44: =I44*(1-'Допущения'!$E$25/4)+$C$20/4*J26 | K44: =J44*(1-'Допущения'!$E$25/4)+$C$20/4*K26 | ... V44: =U44*(1-'Допущения'!$E$25/4)+$C$20/4*V26 | X44: =F44 | Y44: =J44 | Z44: =N44 | AA44: =R44 | AB44: =V44 | AC44: =V44
A45: 8. Доход от моста «Детский банк» → «Старт» | B45: млн ₽ | C45: =C44*$C$14/4/1000000 | D45: =D44*$C$14/4/1000000 | E45: =E44*$C$14/4/1000000 | F45: =F44*$C$14/4/1000000 | G45: =G44*$C$14/4/1000000 | H45: =H44*$C$14/4/1000000 | I45: =I44*$C$14/4/1000000 | J45: =J44*$C$14/4/1000000 | ... V45: =V44*$C$14/4/1000000 | X45: =SUM(C45:F45) | Y45: =SUM(G45:J45) | Z45: =SUM(K45:N45) | AA45: =SUM(O45:R45) | AB45: =SUM(S45:V45) | AC45: =SUM(C45:V45)
A46: Пушкинская карта: новые клиенты через «Старт», накопительно | B46: чел. | C46: =$C$21/4*C26 | D46: =C46*(1-'Допущения'!$E$25/4)+$C$21/4*D26 | E46: =D46*(1-'Допущения'!$E$25/4)+$C$21/4*E26 | F46: =E46*(1-'Допущения'!$E$25/4)+$C$21/4*F26 | G46: =F46*(1-'Допущения'!$E$25/4)+$C$21/4*G26 | H46: =G46*(1-'Допущения'!$E$25/4)+$C$21/4*H26 | I46: =H46*(1-'Допущения'!$E$25/4)+$C$21/4*I26 | J46: =I46*(1-'Допущения'!$E$25/4)+$C$21/4*J26 | K46: =J46*(1-'Допущения'!$E$25/4)+$C$21/4*K26 | ... V46: =U46*(1-'Допущения'!$E$25/4)+$C$21/4*V26 | X46: =F46 | Y46: =J46 | Z46: =N46 | AA46: =R46 | AB46: =V46 | AC46: =V46
A47: 9. Доход от клиентов из «Пушкинской карты» | B47: млн ₽ | C47: =C46*$C$14/4/1000000 | D47: =D46*$C$14/4/1000000 | E47: =E46*$C$14/4/1000000 | F47: =F46*$C$14/4/1000000 | G47: =G46*$C$14/4/1000000 | H47: =H46*$C$14/4/1000000 | I47: =I46*$C$14/4/1000000 | J47: =J46*$C$14/4/1000000 | ... V47: =V46*$C$14/4/1000000 | X47: =SUM(C47:F47) | Y47: =SUM(G47:J47) | Z47: =SUM(K47:N47) | AA47: =SUM(O47:R47) | AB47: =SUM(S47:V47) | AC47: =SUM(C47:V47)
A48: Эффект для банка — этап 2: перехват для клиентов 23+
A49: Предотвращённые дроп-кейсы 23+ | B49: шт. | C49: =$C$18/4*'Допущения'!$E$52*C28 | D49: =$C$18/4*'Допущения'!$E$52*D28 | E49: =$C$18/4*'Допущения'!$E$52*E28 | F49: =$C$18/4*'Допущения'!$E$52*F28 | G49: =$C$18/4*'Допущения'!$E$52*G28 | H49: =$C$18/4*'Допущения'!$E$52*H28 | I49: =$C$18/4*'Допущения'!$E$52*I28 | J49: =$C$18/4*'Допущения'!$E$52*J28 | ... V49: =$C$18/4*'Допущения'!$E$52*V28 | X49: =SUM(C49:F49) | Y49: =SUM(G49:J49) | Z49: =SUM(K49:N49) | AA49: =SUM(O49:R49) | AB49: =SUM(S49:V49) | AC49: =SUM(C49:V49)
A50: 6. Экономия на разборе дроп-кейсов 23+ | B50: млн ₽ | C50: =C49*$C$15/1000000 | D50: =D49*$C$15/1000000 | E50: =E49*$C$15/1000000 | F50: =F49*$C$15/1000000 | G50: =G49*$C$15/1000000 | H50: =H49*$C$15/1000000 | I50: =I49*$C$15/1000000 | J50: =J49*$C$15/1000000 | ... V50: =V49*$C$15/1000000 | X50: =SUM(C50:F50) | Y50: =SUM(G50:J50) | Z50: =SUM(K50:N50) | AA50: =SUM(O50:R50) | AB50: =SUM(S50:V50) | AC50: =SUM(C50:V50)
A51: Сохранённые взрослые клиенты, накопительно | B51: чел. | C51: =C49*'Допущения'!$E$35 | D51: =C51*(1-'Допущения'!$E$54/4)+D49*'Допущения'!$E$35 | E51: =D51*(1-'Допущения'!$E$54/4)+E49*'Допущения'!$E$35 | F51: =E51*(1-'Допущения'!$E$54/4)+F49*'Допущения'!$E$35 | G51: =F51*(1-'Допущения'!$E$54/4)+G49*'Допущения'!$E$35 | H51: =G51*(1-'Допущения'!$E$54/4)+H49*'Допущения'!$E$35 | I51: =H51*(1-'Допущения'!$E$54/4)+I49*'Допущения'!$E$35 | J51: =I51*(1-'Допущения'!$E$54/4)+J49*'Допущения'!$E$35 | K51: =J51*(1-'Допущения'!$E$54/4)+K49*'Допущения'!$E$35 | ... V51: =U51*(1-'Допущения'!$E$54/4)+V49*'Допущения'!$E$35 | X51: =F51 | Y51: =J51 | Z51: =N51 | AA51: =R51 | AB51: =V51 | AC51: =V51
A52: 7. Доход от сохранённых взрослых клиентов | B52: млн ₽ | C52: =C51*'Допущения'!$E$53/4/1000000 | D52: =D51*'Допущения'!$E$53/4/1000000 | E52: =E51*'Допущения'!$E$53/4/1000000 | F52: =F51*'Допущения'!$E$53/4/1000000 | G52: =G51*'Допущения'!$E$53/4/1000000 | H52: =H51*'Допущения'!$E$53/4/1000000 | I52: =I51*'Допущения'!$E$53/4/1000000 | J52: =J51*'Допущения'!$E$53/4/1000000 | ... V52: =V51*'Допущения'!$E$53/4/1000000 | X52: =SUM(C52:F52) | Y52: =SUM(G52:J52) | Z52: =SUM(K52:N52) | AA52: =SUM(O52:R52) | AB52: =SUM(S52:V52) | AC52: =SUM(C52:V52)
A53: ИТОГО ЭФФЕКТ | B53: млн ₽ | C53: =C34+C36+C38+C40+C42+C45+C47+C50+C52 | D53: =D34+D36+D38+D40+D42+D45+D47+D50+D52 | E53: =E34+E36+E38+E40+E42+E45+E47+E50+E52 | F53: =F34+F36+F38+F40+F42+F45+F47+F50+F52 | G53: =G34+G36+G38+G40+G42+G45+G47+G50+G52 | H53: =H34+H36+H38+H40+H42+H45+H47+H50+H52 | I53: =I34+I36+I38+I40+I42+I45+I47+I50+I52 | J53: =J34+J36+J38+J40+J42+J45+J47+J50+J52 | ... V53: =V34+V36+V38+V40+V42+V45+V47+V50+V52 | X53: =SUM(C53:F53) | Y53: =SUM(G53:J53) | Z53: =SUM(K53:N53) | AA53: =SUM(O53:R53) | AB53: =SUM(S53:V53) | AC53: =SUM(C53:V53)
A54: Затраты на внедрение и поддержку
A55: Команда: разработка и пилот | B55: млн ₽ | C55: =C25*SUMPRODUCT('Допущения'!$C$85:$C$93,'Допущения'!$B$85:$B$93)*1000*$C$17*3/1000000 | D55: =D25*SUMPRODUCT('Допущения'!$C$85:$C$93,'Допущения'!$B$85:$B$93)*1000*$C$17*3/1000000 | E55: =E25*SUMPRODUCT('Допущения'!$C$85:$C$93,'Допущения'!$B$85:$B$93)*1000*$C$17*3/1000000 | F55: =F25*SUMPRODUCT('Допущения'!$C$85:$C$93,'Допущения'!$B$85:$B$93)*1000*$C$17*3/1000000 | G55: =G25*SUMPRODUCT('Допущения'!$C$85:$C$93,'Допущения'!$B$85:$B$93)*1000*$C$17*3/1000000 | H55: =H25*SUMPRODUCT('Допущения'!$C$85:$C$93,'Допущения'!$B$85:$B$93)*1000*$C$17*3/1000000 | I55: =I25*SUMPRODUCT('Допущения'!$C$85:$C$93,'Допущения'!$B$85:$B$93)*1000*$C$17*3/1000000 | J55: =J25*SUMPRODUCT('Допущения'!$C$85:$C$93,'Допущения'!$B$85:$B$93)*1000*$C$17*3/1000000 | ... V55: =V25*SUMPRODUCT('Допущения'!$C$85:$C$93,'Допущения'!$B$85:$B$93)*1000*$C$17*3/1000000 | X55: =SUM(C55:F55) | Y55: =SUM(G55:J55) | Z55: =SUM(K55:N55) | AA55: =SUM(O55:R55) | AB55: =SUM(S55:V55) | AC55: =SUM(C55:V55)
A56: Команда: эксплуатация и развитие | B56: млн ₽ | C56: =(1-C25)*SUMPRODUCT('Допущения'!$D$85:$D$93,'Допущения'!$B$85:$B$93)*1000*$C$17*3/1000000 | D56: =(1-D25)*SUMPRODUCT('Допущения'!$D$85:$D$93,'Допущения'!$B$85:$B$93)*1000*$C$17*3/1000000 | E56: =(1-E25)*SUMPRODUCT('Допущения'!$D$85:$D$93,'Допущения'!$B$85:$B$93)*1000*$C$17*3/1000000 | F56: =(1-F25)*SUMPRODUCT('Допущения'!$D$85:$D$93,'Допущения'!$B$85:$B$93)*1000*$C$17*3/1000000 | G56: =(1-G25)*SUMPRODUCT('Допущения'!$D$85:$D$93,'Допущения'!$B$85:$B$93)*1000*$C$17*3/1000000 | H56: =(1-H25)*SUMPRODUCT('Допущения'!$D$85:$D$93,'Допущения'!$B$85:$B$93)*1000*$C$17*3/1000000 | I56: =(1-I25)*SUMPRODUCT('Допущения'!$D$85:$D$93,'Допущения'!$B$85:$B$93)*1000*$C$17*3/1000000 | J56: =(1-J25)*SUMPRODUCT('Допущения'!$D$85:$D$93,'Допущения'!$B$85:$B$93)*1000*$C$17*3/1000000 | ... V56: =(1-V25)*SUMPRODUCT('Допущения'!$D$85:$D$93,'Допущения'!$B$85:$B$93)*1000*$C$17*3/1000000 | X56: =SUM(C56:F56) | Y56: =SUM(G56:J56) | Z56: =SUM(K56:N56) | AA56: =SUM(O56:R56) | AB56: =SUM(S56:V56) | AC56: =SUM(C56:V56)
A57: Инфраструктура, ИБ, контент, маркетинг (график) | B57: млн ₽ | C57: =SUM('Допущения'!C$101:C$106) | D57: =SUM('Допущения'!D$101:D$106) | E57: =SUM('Допущения'!E$101:E$106) | F57: =SUM('Допущения'!F$101:F$106) | G57: =SUM('Допущения'!G$101:G$106) | H57: =SUM('Допущения'!H$101:H$106) | I57: =SUM('Допущения'!I$101:I$106) | J57: =SUM('Допущения'!J$101:J$106) | ... V57: =SUM('Допущения'!V$101:V$106) | X57: =SUM(C57:F57) | Y57: =SUM(G57:J57) | Z57: =SUM(K57:N57) | AA57: =SUM(O57:R57) | AB57: =SUM(S57:V57) | AC57: =SUM(C57:V57)
A58: Мост и «Пушкинская карта»: интеграция и поддержка | B58: млн ₽ | C58: ='Допущения'!C$108*'Допущения'!$E$62+'Допущения'!C$109*'Допущения'!$E$66 | D58: ='Допущения'!D$108*'Допущения'!$E$62+'Допущения'!D$109*'Допущения'!$E$66 | E58: ='Допущения'!E$108*'Допущения'!$E$62+'Допущения'!E$109*'Допущения'!$E$66 | F58: ='Допущения'!F$108*'Допущения'!$E$62+'Допущения'!F$109*'Допущения'!$E$66 | G58: ='Допущения'!G$108*'Допущения'!$E$62+'Допущения'!G$109*'Допущения'!$E$66 | H58: ='Допущения'!H$108*'Допущения'!$E$62+'Допущения'!H$109*'Допущения'!$E$66 | I58: ='Допущения'!I$108*'Допущения'!$E$62+'Допущения'!I$109*'Допущения'!$E$66 | J58: ='Допущения'!J$108*'Допущения'!$E$62+'Допущения'!J$109*'Допущения'!$E$66 | ... V58: ='Допущения'!V$108*'Допущения'!$E$62+'Допущения'!V$109*'Допущения'!$E$66 | X58: =SUM(C58:F58) | Y58: =SUM(G58:J58) | Z58: =SUM(K58:N58) | AA58: =SUM(O58:R58) | AB58: =SUM(S58:V58) | AC58: =SUM(C58:V58)
A59: Этап 2: доработка и поддержка для клиентов 23+ | B59: млн ₽ | C59: ='Допущения'!C$107*'Допущения'!$E$48 | D59: ='Допущения'!D$107*'Допущения'!$E$48 | E59: ='Допущения'!E$107*'Допущения'!$E$48 | F59: ='Допущения'!F$107*'Допущения'!$E$48 | G59: ='Допущения'!G$107*'Допущения'!$E$48 | H59: ='Допущения'!H$107*'Допущения'!$E$48 | I59: ='Допущения'!I$107*'Допущения'!$E$48 | J59: ='Допущения'!J$107*'Допущения'!$E$48 | ... V59: ='Допущения'!V$107*'Допущения'!$E$48 | X59: =SUM(C59:F59) | Y59: =SUM(G59:J59) | Z59: =SUM(K59:N59) | AA59: =SUM(O59:R59) | AB59: =SUM(S59:V59) | AC59: =SUM(C59:V59)
A60: Вознаграждения пользователям | B60: млн ₽ | C60: =C31*1000*'Допущения'!$E$78/4/1000000 | D60: =D31*1000*'Допущения'!$E$78/4/1000000 | E60: =E31*1000*'Допущения'!$E$78/4/1000000 | F60: =F31*1000*'Допущения'!$E$78/4/1000000 | G60: =G31*1000*'Допущения'!$E$78/4/1000000 | H60: =H31*1000*'Допущения'!$E$78/4/1000000 | I60: =I31*1000*'Допущения'!$E$78/4/1000000 | J60: =J31*1000*'Допущения'!$E$78/4/1000000 | ... V60: =V31*1000*'Допущения'!$E$78/4/1000000 | X60: =SUM(C60:F60) | Y60: =SUM(G60:J60) | Z60: =SUM(K60:N60) | AA60: =SUM(O60:R60) | AB60: =SUM(S60:V60) | AC60: =SUM(C60:V60)
A61: Резерв на непредвиденное | B61: млн ₽ | C61: =(C55+C56+C57+C58+C59+C60)*'Допущения'!$E$79 | D61: =(D55+D56+D57+D58+D59+D60)*'Допущения'!$E$79 | E61: =(E55+E56+E57+E58+E59+E60)*'Допущения'!$E$79 | F61: =(F55+F56+F57+F58+F59+F60)*'Допущения'!$E$79 | G61: =(G55+G56+G57+G58+G59+G60)*'Допущения'!$E$79 | H61: =(H55+H56+H57+H58+H59+H60)*'Допущения'!$E$79 | I61: =(I55+I56+I57+I58+I59+I60)*'Допущения'!$E$79 | J61: =(J55+J56+J57+J58+J59+J60)*'Допущения'!$E$79 | ... V61: =(V55+V56+V57+V58+V59+V60)*'Допущения'!$E$79 | X61: =SUM(C61:F61) | Y61: =SUM(G61:J61) | Z61: =SUM(K61:N61) | AA61: =SUM(O61:R61) | AB61: =SUM(S61:V61) | AC61: =SUM(C61:V61)
A62: ИТОГО ЗАТРАТЫ (с учётом перерасхода) | B62: млн ₽ | C62: =(C55+C56+C57+C58+C59+C60+C61)*'Допущения'!$E$80 | D62: =(D55+D56+D57+D58+D59+D60+D61)*'Допущения'!$E$80 | E62: =(E55+E56+E57+E58+E59+E60+E61)*'Допущения'!$E$80 | F62: =(F55+F56+F57+F58+F59+F60+F61)*'Допущения'!$E$80 | G62: =(G55+G56+G57+G58+G59+G60+G61)*'Допущения'!$E$80 | H62: =(H55+H56+H57+H58+H59+H60+H61)*'Допущения'!$E$80 | I62: =(I55+I56+I57+I58+I59+I60+I61)*'Допущения'!$E$80 | J62: =(J55+J56+J57+J58+J59+J60+J61)*'Допущения'!$E$80 | ... V62: =(V55+V56+V57+V58+V59+V60+V61)*'Допущения'!$E$80 | X62: =SUM(C62:F62) | Y62: =SUM(G62:J62) | Z62: =SUM(K62:N62) | AA62: =SUM(O62:R62) | AB62: =SUM(S62:V62) | AC62: =SUM(C62:V62)
A63: Денежный поток
A64: Чистый денежный поток | B64: млн ₽ | C64: =C53-C62 | D64: =D53-D62 | E64: =E53-E62 | F64: =F53-F62 | G64: =G53-G62 | H64: =H53-H62 | I64: =I53-I62 | J64: =J53-J62 | ... V64: =V53-V62 | X64: =SUM(C64:F64) | Y64: =SUM(G64:J64) | Z64: =SUM(K64:N64) | AA64: =SUM(O64:R64) | AB64: =SUM(S64:V64) | AC64: =SUM(C64:V64)
A65: Накопленный денежный поток | B65: млн ₽ | C65: =C64 | D65: =C65+D64 | E65: =D65+E64 | F65: =E65+F64 | G65: =F65+G64 | H65: =G65+H64 | I65: =H65+I64 | J65: =I65+J64 | K65: =J65+K64 | ... V65: =U65+V64 | X65: =F65 | Y65: =J65 | Z65: =N65 | AA65: =R65 | AB65: =V65 | AC65: =V65
A66: Коэффициент дисконтирования | B66: x | C66: =1/(1+$C$16)^C24 | D66: =1/(1+$C$16)^D24 | E66: =1/(1+$C$16)^E24 | F66: =1/(1+$C$16)^F24 | G66: =1/(1+$C$16)^G24 | H66: =1/(1+$C$16)^H24 | I66: =1/(1+$C$16)^I24 | J66: =1/(1+$C$16)^J24 | ... V66: =1/(1+$C$16)^V24
A67: Дисконтированный поток | B67: млн ₽ | C67: =C64*C66 | D67: =D64*D66 | E67: =E64*E66 | F67: =F64*F66 | G67: =G64*G66 | H67: =H64*H66 | I67: =I64*I66 | J67: =J64*J66 | ... V67: =V64*V66 | X67: =SUM(C67:F67) | Y67: =SUM(G67:J67) | Z67: =SUM(K67:N67) | AA67: =SUM(O67:R67) | AB67: =SUM(S67:V67) | AC67: =SUM(C67:V67)
A68: Служебная: номер квартала, если накопленный поток ≥ 0 | B68: № | C68: =IF(C65>=0,C24,99) | D68: =IF(D65>=0,D24,99) | E68: =IF(E65>=0,E24,99) | F68: =IF(F65>=0,F24,99) | G68: =IF(G65>=0,G24,99) | H68: =IF(H65>=0,H24,99) | I68: =IF(I65>=0,I24,99) | J68: =IF(J65>=0,J24,99) | ... V68: =IF(V65>=0,V24,99)
A69: Поток ядра продукта: без этапа 2, моста и «Пушкинской карты» | B69: млн ₽ | C69: =(C53-C50-C52-C45-C47)-(C55+C56+C57+C60)*(1+'Допущения'!$E$79)*'Допущения'!$E$80 | D69: =(D53-D50-D52-D45-D47)-(D55+D56+D57+D60)*(1+'Допущения'!$E$79)*'Допущения'!$E$80 | E69: =(E53-E50-E52-E45-E47)-(E55+E56+E57+E60)*(1+'Допущения'!$E$79)*'Допущения'!$E$80 | F69: =(F53-F50-F52-F45-F47)-(F55+F56+F57+F60)*(1+'Допущения'!$E$79)*'Допущения'!$E$80 | G69: =(G53-G50-G52-G45-G47)-(G55+G56+G57+G60)*(1+'Допущения'!$E$79)*'Допущения'!$E$80 | H69: =(H53-H50-H52-H45-H47)-(H55+H56+H57+H60)*(1+'Допущения'!$E$79)*'Допущения'!$E$80 | I69: =(I53-I50-I52-I45-I47)-(I55+I56+I57+I60)*(1+'Допущения'!$E$79)*'Допущения'!$E$80 | J69: =(J53-J50-J52-J45-J47)-(J55+J56+J57+J60)*(1+'Допущения'!$E$79)*'Допущения'!$E$80 | ... V69: =(V53-V50-V52-V45-V47)-(V55+V56+V57+V60)*(1+'Допущения'!$E$79)*'Допущения'!$E$80 | X69: =SUM(C69:F69) | Y69: =SUM(G69:J69) | Z69: =SUM(K69:N69) | AA69: =SUM(O69:R69) | AB69: =SUM(S69:V69) | AC69: =SUM(C69:V69)
A70: Итоговые показатели сценария
A71: NPV за 5 лет (2027–2031) | B71: млн ₽ | C71: =SUM(C67:V67)
A72: NPV за 5 лет только ядра продукта (без этапа 2, моста и «Пушкинской карты») | B72: млн ₽ | C72: =SUMPRODUCT(C69:V69,C66:V66)
A73: NPV за первые 3 года (2027–2029), справочно | B73: млн ₽ | C73: =SUM(C67:N67)
A74: Суммарный эффект за 5 лет | B74: млн ₽ | C74: =AC53
A75: Суммарные затраты за 5 лет | B75: млн ₽ | C75: =AC62
A76: ROI за 5 лет | B76: доля | C76: =IF(C75>0,(C74-C75)/C75,0)
A77: Инвестиции до полного запуска (разработка + пилот) | B77: млн ₽ | C77: =SUMPRODUCT(C62:V62,C25:V25)
A78: Квартал окупаемости (99 — не окупается за 5 лет) | B78: № | C78: =MIN(C68:V68)
A79: Срок окупаемости от старта проекта | B79: мес. | C79: =IF(C78=99,"больше 60",IF(C78=1,0,(C78-1)*3+3*(-INDEX(C65:V65,C78-1))/INDEX(C64:V64,C78)))
A80: Срок окупаемости от полного запуска | B80: мес. | C80: =IF(C78=99,"больше 60",C79-('Допущения'!$E$75-1)*3)
A81: Годовые затраты в режиме эксплуатации (2031) | B81: млн ₽ | C81: =AB62
A82: Годовой эффект (2031) | B82: млн ₽ | C82: =AB53
A83: Операционный поток 2029 (эффект минус затраты) | B83: млн ₽ | C83: =Z53-Z62
A84: Предотвращено дроп-кейсов молодёжи за 5 лет | B84: шт. | C84: =AC33
A85: Предотвращено дроп-кейсов 23+ за 5 лет | B85: шт. | C85: =AC49
A86: Социальный эффект: чужих денег не прошло через карты ВТБ (вне NPV) | B86: млн ₽ | C86: =(C84+C85)*'Допущения'!$E$36/1000000
A87: MAU раздела на конец 2031 | B87: тыс. чел. | C87: =V31
A88: Молодых клиентов сохранено, удержано и привлечено (на конец 2031) | B88: чел. | C88: =V35+V37+V39+V44+V46
A89: Стратегическая ценность этих клиентов после 23 лет (вне NPV) | B89: млн ₽ | C89: =C88*C19/1000000
A90: Затраты на одного MAU в 2031 | B90: ₽/год | C90: =IF(V31>0,AB62*1000000/(V31*1000),0)
